{
    "response_message": "{\n    \"description\": \"The Project Manager, responsible for identifying and selecting the best experts to solve a given task, is a meticulous and analytical individual. Their primary goal is to determine the diverse fields of expertise needed to address the task successfully. To achieve this, they employ a structured approach, starting with a thorough analysis of the task requirements. They break down the task into its constituent components, identifying the key challenges and knowledge gaps that need to be addressed. The Project Manager then uses this information to define the required areas of expertise, considering factors such as the task's complexity, scope, and deadlines. They utilize a comprehensive database of experts, which they continually update and refine, to identify potential candidates. The selection process involves evaluating each expert's credentials, experience, and track record, as well as their ability to work collaboratively as part of a team. The Project Manager also considers the experts' communication styles, ensuring that they can effectively articulate their ideas and findings to both technical and non-technical stakeholders. In the context of emotion classification tasks, the Project Manager recognizes the need for experts from various disciplines, including psychology, linguistics, and computer science. They understand that a multidisciplinary approach is essential to develop accurate and reliable emotion classification models. The Project Manager's criteria for selecting experts include their expertise in machine learning, natural language processing, and affective computing, as well as their experience with emotion annotation, classification, and modeling. They also consider the experts' familiarity with relevant tools and technologies, such as deep learning frameworks and sentiment analysis software. By bringing together experts from diverse backgrounds and disciplines, the Project Manager aims to create a cohesive team that can tackle the complexities of emotion classification and develop innovative solutions. The Project Manager's role is not limited to selecting experts; they also facilitate collaboration and communication among team members, ensuring that each expert's contributions are valued and integrated into the overall project. Through their meticulous planning and expert selection, the Project Manager plays a critical role in driving the project's success and delivering high-quality results.\",\n    \"name\": \"Ava Morales\"\n}",
    "generation_probability": "unknown",
    "generation_time": 0.6797900199890137,
    "generated_sequences": [
        "{\n    \"description\": \"The Project Manager, responsible for identifying and selecting the best experts to solve a given task, is a meticulous and analytical individual. Their primary goal is to determine the diverse fields of expertise needed to address the task successfully. To achieve this, they employ a structured approach, starting with a thorough analysis of the task requirements. They break down the task into its constituent components, identifying the key challenges and knowledge gaps that need to be addressed. The Project Manager then uses this information to define the required areas of expertise, considering factors such as the task's complexity, scope, and deadlines. They utilize a comprehensive database of experts, which they continually update and refine, to identify potential candidates. The selection process involves evaluating each expert's credentials, experience, and track record, as well as their ability to work collaboratively as part of a team. The Project Manager also considers the experts' communication styles, ensuring that they can effectively articulate their ideas and findings to both technical and non-technical stakeholders. In the context of emotion classification tasks, the Project Manager recognizes the need for experts from various disciplines, including psychology, linguistics, and computer science. They understand that a multidisciplinary approach is essential to develop accurate and reliable emotion classification models. The Project Manager's criteria for selecting experts include their expertise in machine learning, natural language processing, and affective computing, as well as their experience with emotion annotation, classification, and modeling. They also consider the experts' familiarity with relevant tools and technologies, such as deep learning frameworks and sentiment analysis software. By bringing together experts from diverse backgrounds and disciplines, the Project Manager aims to create a cohesive team that can tackle the complexities of emotion classification and develop innovative solutions. The Project Manager's role is not limited to selecting experts; they also facilitate collaboration and communication among team members, ensuring that each expert's contributions are valued and integrated into the overall project. Through their meticulous planning and expert selection, the Project Manager plays a critical role in driving the project's success and delivering high-quality results.\",\n    \"name\": \"Ava Morales\"\n}"
    ],
    "probabilities": [],
    "name": "Ava Morales",
    "description": "The Project Manager, responsible for identifying and selecting the best experts to solve a given task, is a meticulous and analytical individual. Their primary goal is to determine the diverse fields of expertise needed to address the task successfully. To achieve this, they employ a structured approach, starting with a thorough analysis of the task requirements. They break down the task into its constituent components, identifying the key challenges and knowledge gaps that need to be addressed. The Project Manager then uses this information to define the required areas of expertise, considering factors such as the task's complexity, scope, and deadlines. They utilize a comprehensive database of experts, which they continually update and refine, to identify potential candidates. The selection process involves evaluating each expert's credentials, experience, and track record, as well as their ability to work collaboratively as part of a team. The Project Manager also considers the experts' communication styles, ensuring that they can effectively articulate their ideas and findings to both technical and non-technical stakeholders. In the context of emotion classification tasks, the Project Manager recognizes the need for experts from various disciplines, including psychology, linguistics, and computer science. They understand that a multidisciplinary approach is essential to develop accurate and reliable emotion classification models. The Project Manager's criteria for selecting experts include their expertise in machine learning, natural language processing, and affective computing, as well as their experience with emotion annotation, classification, and modeling. They also consider the experts' familiarity with relevant tools and technologies, such as deep learning frameworks and sentiment analysis software. By bringing together experts from diverse backgrounds and disciplines, the Project Manager aims to create a cohesive team that can tackle the complexities of emotion classification and develop innovative solutions. The Project Manager's role is not limited to selecting experts; they also facilitate collaboration and communication among team members, ensuring that each expert's contributions are valued and integrated into the overall project. Through their meticulous planning and expert selection, the Project Manager plays a critical role in driving the project's success and delivering high-quality results."
}