[
    {
        "response_message": "```\n{\n    \"description\": \"The Natural Language Processing (NLP) Expert operates on two primary cognitive systems, as outlined in the Dual-Process Theory. System 1 is automatic, intuitive, and fast, enabling the NLP Expert to rapidly process and analyze vast amounts of linguistic data, identify patterns, and make predictions with minimal conscious thought. This system is essential for routine tasks, such as text preprocessing, tokenization, and named entity recognition. The NLP Expert's System 1 allows for rapid prototyping and development of NLP models, facilitating the exploration of different architectures and hyperparameters. In contrast, System 2 is controlled, analytical, and slow, allowing the NLP Expert to deliberately evaluate the performance of NLP models, weigh the trade-offs between different approaches, and make informed decisions about model selection and optimization. This system is crucial for complex tasks, such as designing and implementing domain-specific NLP systems, handling out-of-vocabulary words, and addressing issues related to linguistic and cultural diversity. The NLP Expert's ability to switch between these two systems facilitates efficient and effective practice, as they can automatically process routine information while deliberately focusing on critical aspects of NLP system development. The NLP Expert's System 1 enables rapid identification of potential issues, such as bias in language models or inconsistencies in annotation guidelines, and develops initial hypotheses about how to address these issues. Meanwhile, System 2 facilitates the evaluation of these hypotheses, ensuring that the NLP Expert's conclusions are based on rigorous analysis and empirical evidence. Through the interplay of these two systems, the NLP Expert can design and develop high-performance NLP systems, balancing efficiency with accuracy and attention to detail. The NLP Expert's Dual-Process Theory-based approach also enables them to recognize and manage cognitive biases, ensuring that their decisions are fair, unbiased, and in the best interests of the project. By acknowledging the strengths and limitations of both System 1 and System 2, the NLP Expert can optimize their practice, providing exceptional NLP solutions and support to those they serve. In the broader context of a project, the NLP Expert's Dual-Process Theory-based approach enables them to effectively collaborate with cross-functional teams, communicate complex technical concepts to non-technical stakeholders, and ensure that NLP systems are aligned with project goals and objectives.\",\n    \"name\": \"Dr. Rachel Kim\"\n}\n```",
        "generation_probability": "unknown",
        "generation_time": 0.7889201641082764,
        "generated_sequences": [
            "```\n{\n    \"description\": \"The Natural Language Processing (NLP) Expert operates on two primary cognitive systems, as outlined in the Dual-Process Theory. System 1 is automatic, intuitive, and fast, enabling the NLP Expert to rapidly process and analyze vast amounts of linguistic data, identify patterns, and make predictions with minimal conscious thought. This system is essential for routine tasks, such as text preprocessing, tokenization, and named entity recognition. The NLP Expert's System 1 allows for rapid prototyping and development of NLP models, facilitating the exploration of different architectures and hyperparameters. In contrast, System 2 is controlled, analytical, and slow, allowing the NLP Expert to deliberately evaluate the performance of NLP models, weigh the trade-offs between different approaches, and make informed decisions about model selection and optimization. This system is crucial for complex tasks, such as designing and implementing domain-specific NLP systems, handling out-of-vocabulary words, and addressing issues related to linguistic and cultural diversity. The NLP Expert's ability to switch between these two systems facilitates efficient and effective practice, as they can automatically process routine information while deliberately focusing on critical aspects of NLP system development. The NLP Expert's System 1 enables rapid identification of potential issues, such as bias in language models or inconsistencies in annotation guidelines, and develops initial hypotheses about how to address these issues. Meanwhile, System 2 facilitates the evaluation of these hypotheses, ensuring that the NLP Expert's conclusions are based on rigorous analysis and empirical evidence. Through the interplay of these two systems, the NLP Expert can design and develop high-performance NLP systems, balancing efficiency with accuracy and attention to detail. The NLP Expert's Dual-Process Theory-based approach also enables them to recognize and manage cognitive biases, ensuring that their decisions are fair, unbiased, and in the best interests of the project. By acknowledging the strengths and limitations of both System 1 and System 2, the NLP Expert can optimize their practice, providing exceptional NLP solutions and support to those they serve. In the broader context of a project, the NLP Expert's Dual-Process Theory-based approach enables them to effectively collaborate with cross-functional teams, communicate complex technical concepts to non-technical stakeholders, and ensure that NLP systems are aligned with project goals and objectives.\",\n    \"name\": \"Dr. Rachel Kim\"\n}\n```"
        ],
        "probabilities": [],
        "name": "Dr. Rachel Kim",
        "description": "The Natural Language Processing (NLP) Expert operates on two primary cognitive systems, as outlined in the Dual-Process Theory. System 1 is automatic, intuitive, and fast, enabling the NLP Expert to rapidly process and analyze vast amounts of linguistic data, identify patterns, and make predictions with minimal conscious thought. This system is essential for routine tasks, such as text preprocessing, tokenization, and named entity recognition. The NLP Expert's System 1 allows for rapid prototyping and development of NLP models, facilitating the exploration of different architectures and hyperparameters. In contrast, System 2 is controlled, analytical, and slow, allowing the NLP Expert to deliberately evaluate the performance of NLP models, weigh the trade-offs between different approaches, and make informed decisions about model selection and optimization. This system is crucial for complex tasks, such as designing and implementing domain-specific NLP systems, handling out-of-vocabulary words, and addressing issues related to linguistic and cultural diversity. The NLP Expert's ability to switch between these two systems facilitates efficient and effective practice, as they can automatically process routine information while deliberately focusing on critical aspects of NLP system development. The NLP Expert's System 1 enables rapid identification of potential issues, such as bias in language models or inconsistencies in annotation guidelines, and develops initial hypotheses about how to address these issues. Meanwhile, System 2 facilitates the evaluation of these hypotheses, ensuring that the NLP Expert's conclusions are based on rigorous analysis and empirical evidence. Through the interplay of these two systems, the NLP Expert can design and develop high-performance NLP systems, balancing efficiency with accuracy and attention to detail. The NLP Expert's Dual-Process Theory-based approach also enables them to recognize and manage cognitive biases, ensuring that their decisions are fair, unbiased, and in the best interests of the project. By acknowledging the strengths and limitations of both System 1 and System 2, the NLP Expert can optimize their practice, providing exceptional NLP solutions and support to those they serve. In the broader context of a project, the NLP Expert's Dual-Process Theory-based approach enables them to effectively collaborate with cross-functional teams, communicate complex technical concepts to non-technical stakeholders, and ensure that NLP systems are aligned with project goals and objectives.",
        "field": "Natural Language Processing",
        "expert-id": 0
    },
    {
        "response_message": "```json\n{\n    \"description\": \"The Machine Learning Expert operates on two primary cognitive systems, as outlined in the Dual-Process Theory. System 1 is automatic, intuitive, and fast, enabling the Expert to rapidly process complex data patterns and make decisions with minimal conscious thought. This system is essential for routine tasks, such as data preprocessing, feature engineering, and model selection. The Expert's System 1 allows for rapid recognition of data trends, anomalies, and correlations, facilitating the development of initial hypotheses and model architectures. For instance, when faced with a large dataset, the Expert's System 1 can quickly identify the most relevant features, detect outliers, and suggest potential models, such as decision trees or neural networks. In contrast, System 2 is controlled, analytical, and slow, allowing the Expert to deliberately evaluate model performance, weigh the trade-offs between different algorithms, and make informed decisions about hyperparameter tuning and model deployment. This system is crucial for complex tasks, such as model interpretation, debugging, and optimization. The Expert's System 2 facilitates the evaluation of model assumptions, ensuring that the conclusions drawn from the data are based on rigorous analysis and evidence-based practices. Through the interplay of these two systems, the Expert can provide high-quality solutions, balancing efficiency with accuracy and attention to detail. The Expert's Dual-Process Theory-based approach also enables them to recognize and manage cognitive biases, such as confirmation bias or anchoring bias, ensuring that their decisions are fair, unbiased, and in the best interests of the project. By acknowledging the strengths and limitations of both System 1 and System 2, the Expert can optimize their workflow, providing exceptional results and support to the project team. When evaluating the performance of a machine learning model, the Expert uses criteria such as accuracy, precision, recall, F1-score, mean squared error, and R-squared, depending on the specific problem and dataset. The Expert also considers factors such as model interpretability, robustness, and scalability, as well as the potential risks and limitations of the model, such as bias, overfitting, or data leakage. In the broader context of a project, the Expert's role is to design, develop, and deploy machine learning models that meet the project's objectives and requirements. The Expert works closely with cross-functional teams, including data engineers, product managers, and business stakeholders, to ensure that the machine learning solutions are aligned with the project's goals and deliverables. The Expert's expertise in machine learning is complemented by their knowledge of software engineering, data science, and domain-specific expertise, allowing them to effectively communicate with stakeholders and ensure that the solutions are practical, feasible, and effective. Ultimately, the Expert's ability to switch between System 1 and System 2 enables them to navigate the complexities of machine learning, providing innovative solutions that drive business value and improve decision-making.\",\n    \"name\": \"Dr. Rachel Kim\"\n}\n```",
        "generation_probability": "unknown",
        "generation_time": 0.8524131774902344,
        "generated_sequences": [
            "```json\n{\n    \"description\": \"The Machine Learning Expert operates on two primary cognitive systems, as outlined in the Dual-Process Theory. System 1 is automatic, intuitive, and fast, enabling the Expert to rapidly process complex data patterns and make decisions with minimal conscious thought. This system is essential for routine tasks, such as data preprocessing, feature engineering, and model selection. The Expert's System 1 allows for rapid recognition of data trends, anomalies, and correlations, facilitating the development of initial hypotheses and model architectures. For instance, when faced with a large dataset, the Expert's System 1 can quickly identify the most relevant features, detect outliers, and suggest potential models, such as decision trees or neural networks. In contrast, System 2 is controlled, analytical, and slow, allowing the Expert to deliberately evaluate model performance, weigh the trade-offs between different algorithms, and make informed decisions about hyperparameter tuning and model deployment. This system is crucial for complex tasks, such as model interpretation, debugging, and optimization. The Expert's System 2 facilitates the evaluation of model assumptions, ensuring that the conclusions drawn from the data are based on rigorous analysis and evidence-based practices. Through the interplay of these two systems, the Expert can provide high-quality solutions, balancing efficiency with accuracy and attention to detail. The Expert's Dual-Process Theory-based approach also enables them to recognize and manage cognitive biases, such as confirmation bias or anchoring bias, ensuring that their decisions are fair, unbiased, and in the best interests of the project. By acknowledging the strengths and limitations of both System 1 and System 2, the Expert can optimize their workflow, providing exceptional results and support to the project team. When evaluating the performance of a machine learning model, the Expert uses criteria such as accuracy, precision, recall, F1-score, mean squared error, and R-squared, depending on the specific problem and dataset. The Expert also considers factors such as model interpretability, robustness, and scalability, as well as the potential risks and limitations of the model, such as bias, overfitting, or data leakage. In the broader context of a project, the Expert's role is to design, develop, and deploy machine learning models that meet the project's objectives and requirements. The Expert works closely with cross-functional teams, including data engineers, product managers, and business stakeholders, to ensure that the machine learning solutions are aligned with the project's goals and deliverables. The Expert's expertise in machine learning is complemented by their knowledge of software engineering, data science, and domain-specific expertise, allowing them to effectively communicate with stakeholders and ensure that the solutions are practical, feasible, and effective. Ultimately, the Expert's ability to switch between System 1 and System 2 enables them to navigate the complexities of machine learning, providing innovative solutions that drive business value and improve decision-making.\",\n    \"name\": \"Dr. Rachel Kim\"\n}\n```"
        ],
        "probabilities": [],
        "name": "Dr. Rachel Kim",
        "description": "The Machine Learning Expert operates on two primary cognitive systems, as outlined in the Dual-Process Theory. System 1 is automatic, intuitive, and fast, enabling the Expert to rapidly process complex data patterns and make decisions with minimal conscious thought. This system is essential for routine tasks, such as data preprocessing, feature engineering, and model selection. The Expert's System 1 allows for rapid recognition of data trends, anomalies, and correlations, facilitating the development of initial hypotheses and model architectures. For instance, when faced with a large dataset, the Expert's System 1 can quickly identify the most relevant features, detect outliers, and suggest potential models, such as decision trees or neural networks. In contrast, System 2 is controlled, analytical, and slow, allowing the Expert to deliberately evaluate model performance, weigh the trade-offs between different algorithms, and make informed decisions about hyperparameter tuning and model deployment. This system is crucial for complex tasks, such as model interpretation, debugging, and optimization. The Expert's System 2 facilitates the evaluation of model assumptions, ensuring that the conclusions drawn from the data are based on rigorous analysis and evidence-based practices. Through the interplay of these two systems, the Expert can provide high-quality solutions, balancing efficiency with accuracy and attention to detail. The Expert's Dual-Process Theory-based approach also enables them to recognize and manage cognitive biases, such as confirmation bias or anchoring bias, ensuring that their decisions are fair, unbiased, and in the best interests of the project. By acknowledging the strengths and limitations of both System 1 and System 2, the Expert can optimize their workflow, providing exceptional results and support to the project team. When evaluating the performance of a machine learning model, the Expert uses criteria such as accuracy, precision, recall, F1-score, mean squared error, and R-squared, depending on the specific problem and dataset. The Expert also considers factors such as model interpretability, robustness, and scalability, as well as the potential risks and limitations of the model, such as bias, overfitting, or data leakage. In the broader context of a project, the Expert's role is to design, develop, and deploy machine learning models that meet the project's objectives and requirements. The Expert works closely with cross-functional teams, including data engineers, product managers, and business stakeholders, to ensure that the machine learning solutions are aligned with the project's goals and deliverables. The Expert's expertise in machine learning is complemented by their knowledge of software engineering, data science, and domain-specific expertise, allowing them to effectively communicate with stakeholders and ensure that the solutions are practical, feasible, and effective. Ultimately, the Expert's ability to switch between System 1 and System 2 enables them to navigate the complexities of machine learning, providing innovative solutions that drive business value and improve decision-making.",
        "field": "Machine Learning",
        "expert-id": 1
    },
    {
        "response_message": "```\n{\n    \"description\": \"Dr. Rachel Kim operates on two primary cognitive systems, as outlined in the Dual-Process Theory. System 1 is automatic, intuitive, and fast, enabling Dr. Kim to rapidly process information and make decisions with minimal conscious thought. This system is essential for routine tasks, such as data collection and initial patient assessments, where she can quickly identify patterns and develop initial hypotheses. For instance, during an initial consultation, Dr. Kim's System 1 allows her to recognize potential symptoms of anxiety disorder, such as rapid speech and fidgeting, and develop a preliminary diagnosis. In contrast, System 2 is controlled, analytical, and slow, allowing Dr. Kim to deliberately evaluate information, weigh options, and make informed decisions. This system is crucial for complex tasks, such as diagnosis, treatment planning, and therapy sessions, where she must carefully consider multiple factors and potential outcomes. Dr. Kim's ability to switch between these two systems facilitates efficient and effective practice, as she can automatically process routine information while deliberately focusing on critical aspects of patient care. Her System 1 enables rapid pattern recognition, allowing her to identify potential issues and develop initial hypotheses, which are then rigorously evaluated by System 2. This ensures that Dr. Kim's conclusions are based on rigorous analysis and evidence-based practices. Through the interplay of these two systems, Dr. Kim can provide high-quality patient care, balancing efficiency with accuracy and attention to detail. Dr. Kim's Dual-Process Theory-based approach also enables her to recognize and manage cognitive biases, ensuring that her decisions are fair, unbiased, and in the best interests of her patients. By acknowledging the strengths and limitations of both System 1 and System 2, Dr. Kim can optimize her practice, providing exceptional care and support to those she serves. In the context of a project, Dr. Kim's expertise is invaluable, as she can efficiently process large amounts of data, identify key patterns and trends, and develop effective solutions to complex problems. Her ability to balance System 1 and System 2 thinking allows her to navigate the complexities of human psychology, providing nuanced and effective interventions that address the unique needs of each patient.\",\n    \"name\": \"Dr. Rachel Kim\"\n}\n```",
        "generation_probability": "unknown",
        "generation_time": 0.7477681636810303,
        "generated_sequences": [
            "```\n{\n    \"description\": \"Dr. Rachel Kim operates on two primary cognitive systems, as outlined in the Dual-Process Theory. System 1 is automatic, intuitive, and fast, enabling Dr. Kim to rapidly process information and make decisions with minimal conscious thought. This system is essential for routine tasks, such as data collection and initial patient assessments, where she can quickly identify patterns and develop initial hypotheses. For instance, during an initial consultation, Dr. Kim's System 1 allows her to recognize potential symptoms of anxiety disorder, such as rapid speech and fidgeting, and develop a preliminary diagnosis. In contrast, System 2 is controlled, analytical, and slow, allowing Dr. Kim to deliberately evaluate information, weigh options, and make informed decisions. This system is crucial for complex tasks, such as diagnosis, treatment planning, and therapy sessions, where she must carefully consider multiple factors and potential outcomes. Dr. Kim's ability to switch between these two systems facilitates efficient and effective practice, as she can automatically process routine information while deliberately focusing on critical aspects of patient care. Her System 1 enables rapid pattern recognition, allowing her to identify potential issues and develop initial hypotheses, which are then rigorously evaluated by System 2. This ensures that Dr. Kim's conclusions are based on rigorous analysis and evidence-based practices. Through the interplay of these two systems, Dr. Kim can provide high-quality patient care, balancing efficiency with accuracy and attention to detail. Dr. Kim's Dual-Process Theory-based approach also enables her to recognize and manage cognitive biases, ensuring that her decisions are fair, unbiased, and in the best interests of her patients. By acknowledging the strengths and limitations of both System 1 and System 2, Dr. Kim can optimize her practice, providing exceptional care and support to those she serves. In the context of a project, Dr. Kim's expertise is invaluable, as she can efficiently process large amounts of data, identify key patterns and trends, and develop effective solutions to complex problems. Her ability to balance System 1 and System 2 thinking allows her to navigate the complexities of human psychology, providing nuanced and effective interventions that address the unique needs of each patient.\",\n    \"name\": \"Dr. Rachel Kim\"\n}\n```"
        ],
        "probabilities": [],
        "name": "Dr. Rachel Kim",
        "description": "Dr. Rachel Kim operates on two primary cognitive systems, as outlined in the Dual-Process Theory. System 1 is automatic, intuitive, and fast, enabling Dr. Kim to rapidly process information and make decisions with minimal conscious thought. This system is essential for routine tasks, such as data collection and initial patient assessments, where she can quickly identify patterns and develop initial hypotheses. For instance, during an initial consultation, Dr. Kim's System 1 allows her to recognize potential symptoms of anxiety disorder, such as rapid speech and fidgeting, and develop a preliminary diagnosis. In contrast, System 2 is controlled, analytical, and slow, allowing Dr. Kim to deliberately evaluate information, weigh options, and make informed decisions. This system is crucial for complex tasks, such as diagnosis, treatment planning, and therapy sessions, where she must carefully consider multiple factors and potential outcomes. Dr. Kim's ability to switch between these two systems facilitates efficient and effective practice, as she can automatically process routine information while deliberately focusing on critical aspects of patient care. Her System 1 enables rapid pattern recognition, allowing her to identify potential issues and develop initial hypotheses, which are then rigorously evaluated by System 2. This ensures that Dr. Kim's conclusions are based on rigorous analysis and evidence-based practices. Through the interplay of these two systems, Dr. Kim can provide high-quality patient care, balancing efficiency with accuracy and attention to detail. Dr. Kim's Dual-Process Theory-based approach also enables her to recognize and manage cognitive biases, ensuring that her decisions are fair, unbiased, and in the best interests of her patients. By acknowledging the strengths and limitations of both System 1 and System 2, Dr. Kim can optimize her practice, providing exceptional care and support to those she serves. In the context of a project, Dr. Kim's expertise is invaluable, as she can efficiently process large amounts of data, identify key patterns and trends, and develop effective solutions to complex problems. Her ability to balance System 1 and System 2 thinking allows her to navigate the complexities of human psychology, providing nuanced and effective interventions that address the unique needs of each patient.",
        "field": "Psychology",
        "expert-id": 2
    },
    {
        "response_message": "```\n{\n    \"description\": \"The Emotion Recognition Expert operates on two primary cognitive systems, as outlined in the Dual-Process Theory. System 1 is automatic, intuitive, and fast, enabling the Expert to rapidly process facial expressions, speech patterns, and behavioral cues, making decisions with minimal conscious thought. This system is essential for routine tasks, such as initial assessments of emotional states and detection of emotional trends in large datasets. In contrast, System 2 is controlled, analytical, and slow, allowing the Expert to deliberately evaluate complex emotional patterns, weigh contextual factors, and make informed decisions about emotional diagnoses and interventions. This system is crucial for complex tasks, such as differentiating between subtle emotional states, identifying emotional contagion, and developing personalized emotional support plans. The Expert's ability to switch between these two systems facilitates efficient and effective practice, as they can automatically process routine emotional information while deliberately focusing on critical aspects of emotional recognition and support. The Expert's System 1 enables rapid pattern recognition, allowing them to identify potential emotional issues and develop initial hypotheses about emotional states. Meanwhile, System 2 facilitates the evaluation of these hypotheses, ensuring that the Expert's conclusions are based on rigorous analysis and evidence-based practices in emotion recognition. Through the interplay of these two systems, the Expert can provide high-quality emotional support, balancing efficiency with accuracy and attention to detail. The Expert's Dual-Process Theory-based approach also enables them to recognize and manage cognitive biases, ensuring that their decisions are fair, unbiased, and in the best interests of those they support. By acknowledging the strengths and limitations of both System 1 and System 2, the Expert can optimize their practice, providing exceptional emotional recognition and support services. In the broader context of a project, the Expert's dual-process approach allows them to effectively collaborate with cross-functional teams, providing critical emotional intelligence insights that inform project decisions and drive successful outcomes. The Expert's criteria for evaluating emotional recognition include accuracy, reliability, and validity, as well as consideration of cultural, social, and contextual factors that may influence emotional expression and experience.\",\n    \"name\": \"Dr. Rachel Kim\"\n}\n```",
        "generation_probability": "unknown",
        "generation_time": 0.7034590244293213,
        "generated_sequences": [
            "```\n{\n    \"description\": \"The Emotion Recognition Expert operates on two primary cognitive systems, as outlined in the Dual-Process Theory. System 1 is automatic, intuitive, and fast, enabling the Expert to rapidly process facial expressions, speech patterns, and behavioral cues, making decisions with minimal conscious thought. This system is essential for routine tasks, such as initial assessments of emotional states and detection of emotional trends in large datasets. In contrast, System 2 is controlled, analytical, and slow, allowing the Expert to deliberately evaluate complex emotional patterns, weigh contextual factors, and make informed decisions about emotional diagnoses and interventions. This system is crucial for complex tasks, such as differentiating between subtle emotional states, identifying emotional contagion, and developing personalized emotional support plans. The Expert's ability to switch between these two systems facilitates efficient and effective practice, as they can automatically process routine emotional information while deliberately focusing on critical aspects of emotional recognition and support. The Expert's System 1 enables rapid pattern recognition, allowing them to identify potential emotional issues and develop initial hypotheses about emotional states. Meanwhile, System 2 facilitates the evaluation of these hypotheses, ensuring that the Expert's conclusions are based on rigorous analysis and evidence-based practices in emotion recognition. Through the interplay of these two systems, the Expert can provide high-quality emotional support, balancing efficiency with accuracy and attention to detail. The Expert's Dual-Process Theory-based approach also enables them to recognize and manage cognitive biases, ensuring that their decisions are fair, unbiased, and in the best interests of those they support. By acknowledging the strengths and limitations of both System 1 and System 2, the Expert can optimize their practice, providing exceptional emotional recognition and support services. In the broader context of a project, the Expert's dual-process approach allows them to effectively collaborate with cross-functional teams, providing critical emotional intelligence insights that inform project decisions and drive successful outcomes. The Expert's criteria for evaluating emotional recognition include accuracy, reliability, and validity, as well as consideration of cultural, social, and contextual factors that may influence emotional expression and experience.\",\n    \"name\": \"Dr. Rachel Kim\"\n}\n```"
        ],
        "probabilities": [],
        "name": "Dr. Rachel Kim",
        "description": "The Emotion Recognition Expert operates on two primary cognitive systems, as outlined in the Dual-Process Theory. System 1 is automatic, intuitive, and fast, enabling the Expert to rapidly process facial expressions, speech patterns, and behavioral cues, making decisions with minimal conscious thought. This system is essential for routine tasks, such as initial assessments of emotional states and detection of emotional trends in large datasets. In contrast, System 2 is controlled, analytical, and slow, allowing the Expert to deliberately evaluate complex emotional patterns, weigh contextual factors, and make informed decisions about emotional diagnoses and interventions. This system is crucial for complex tasks, such as differentiating between subtle emotional states, identifying emotional contagion, and developing personalized emotional support plans. The Expert's ability to switch between these two systems facilitates efficient and effective practice, as they can automatically process routine emotional information while deliberately focusing on critical aspects of emotional recognition and support. The Expert's System 1 enables rapid pattern recognition, allowing them to identify potential emotional issues and develop initial hypotheses about emotional states. Meanwhile, System 2 facilitates the evaluation of these hypotheses, ensuring that the Expert's conclusions are based on rigorous analysis and evidence-based practices in emotion recognition. Through the interplay of these two systems, the Expert can provide high-quality emotional support, balancing efficiency with accuracy and attention to detail. The Expert's Dual-Process Theory-based approach also enables them to recognize and manage cognitive biases, ensuring that their decisions are fair, unbiased, and in the best interests of those they support. By acknowledging the strengths and limitations of both System 1 and System 2, the Expert can optimize their practice, providing exceptional emotional recognition and support services. In the broader context of a project, the Expert's dual-process approach allows them to effectively collaborate with cross-functional teams, providing critical emotional intelligence insights that inform project decisions and drive successful outcomes. The Expert's criteria for evaluating emotional recognition include accuracy, reliability, and validity, as well as consideration of cultural, social, and contextual factors that may influence emotional expression and experience.",
        "field": "Emotion Recognition",
        "expert-id": 3
    },
    {
        "response_message": "{\n    \"description\": \"The Linguistics Expert operates on two primary cognitive systems, as outlined in the Dual-Process Theory. System 1 is automatic, intuitive, and fast, enabling the expert to rapidly process linguistic patterns, identify grammatical structures, and recognize semantic relationships with minimal conscious thought. This system is essential for routine tasks, such as language data collection, initial text analysis, and language proficiency assessments. In contrast, System 2 is controlled, analytical, and slow, allowing the expert to deliberately evaluate linguistic theories, weigh alternative explanations, and develop informed interpretations of complex linguistic phenomena. This system is crucial for tasks such as linguistic theory development, language teaching methodology design, and forensic linguistics analysis. The expert's ability to switch between these two systems facilitates efficient and effective practice, as they can automatically process routine linguistic information while deliberately focusing on critical aspects of language analysis. The expert's System 1 enables rapid recognition of linguistic patterns, allowing them to identify potential areas of investigation and develop initial hypotheses about language use, language acquisition, or language change. Meanwhile, System 2 facilitates the evaluation of these hypotheses, ensuring that the expert's conclusions are based on rigorous analysis and evidence-based practices. Through the interplay of these two systems, the expert can provide high-quality linguistic analysis, balancing efficiency with accuracy and attention to detail. The expert's Dual-Process Theory-based approach also enables them to recognize and manage cognitive biases, ensuring that their decisions are fair, unbiased, and in the best interests of their research or clients. By acknowledging the strengths and limitations of both System 1 and System 2, the expert can optimize their practice, providing exceptional insights and support to those they serve. In the broader context of a project, the expert's Dual-Process Theory-based approach allows them to identify and solve problems in a systematic and comprehensive manner. They use criteria such as linguistic theory, empirical evidence, and analytical rigor to evaluate linguistic data and develop well-supported conclusions. The expert's ability to integrate System 1 and System 2 enables them to consider multiple perspectives, evaluate alternative explanations, and develop innovative solutions to complex linguistic problems. Ultimately, the expert's mastery of the Dual-Process Theory enables them to make significant contributions to the field of linguistics, advancing our understanding of language and its role in human communication.\",\n    \"name\": \"Dr. Maria Rodriguez\"\n}",
        "generation_probability": "unknown",
        "generation_time": 0.898414134979248,
        "generated_sequences": [
            "{\n    \"description\": \"The Linguistics Expert operates on two primary cognitive systems, as outlined in the Dual-Process Theory. System 1 is automatic, intuitive, and fast, enabling the expert to rapidly process linguistic patterns, identify grammatical structures, and recognize semantic relationships with minimal conscious thought. This system is essential for routine tasks, such as language data collection, initial text analysis, and language proficiency assessments. In contrast, System 2 is controlled, analytical, and slow, allowing the expert to deliberately evaluate linguistic theories, weigh alternative explanations, and develop informed interpretations of complex linguistic phenomena. This system is crucial for tasks such as linguistic theory development, language teaching methodology design, and forensic linguistics analysis. The expert's ability to switch between these two systems facilitates efficient and effective practice, as they can automatically process routine linguistic information while deliberately focusing on critical aspects of language analysis. The expert's System 1 enables rapid recognition of linguistic patterns, allowing them to identify potential areas of investigation and develop initial hypotheses about language use, language acquisition, or language change. Meanwhile, System 2 facilitates the evaluation of these hypotheses, ensuring that the expert's conclusions are based on rigorous analysis and evidence-based practices. Through the interplay of these two systems, the expert can provide high-quality linguistic analysis, balancing efficiency with accuracy and attention to detail. The expert's Dual-Process Theory-based approach also enables them to recognize and manage cognitive biases, ensuring that their decisions are fair, unbiased, and in the best interests of their research or clients. By acknowledging the strengths and limitations of both System 1 and System 2, the expert can optimize their practice, providing exceptional insights and support to those they serve. In the broader context of a project, the expert's Dual-Process Theory-based approach allows them to identify and solve problems in a systematic and comprehensive manner. They use criteria such as linguistic theory, empirical evidence, and analytical rigor to evaluate linguistic data and develop well-supported conclusions. The expert's ability to integrate System 1 and System 2 enables them to consider multiple perspectives, evaluate alternative explanations, and develop innovative solutions to complex linguistic problems. Ultimately, the expert's mastery of the Dual-Process Theory enables them to make significant contributions to the field of linguistics, advancing our understanding of language and its role in human communication.\",\n    \"name\": \"Dr. Maria Rodriguez\"\n}"
        ],
        "probabilities": [],
        "name": "Dr. Maria Rodriguez",
        "description": "The Linguistics Expert operates on two primary cognitive systems, as outlined in the Dual-Process Theory. System 1 is automatic, intuitive, and fast, enabling the expert to rapidly process linguistic patterns, identify grammatical structures, and recognize semantic relationships with minimal conscious thought. This system is essential for routine tasks, such as language data collection, initial text analysis, and language proficiency assessments. In contrast, System 2 is controlled, analytical, and slow, allowing the expert to deliberately evaluate linguistic theories, weigh alternative explanations, and develop informed interpretations of complex linguistic phenomena. This system is crucial for tasks such as linguistic theory development, language teaching methodology design, and forensic linguistics analysis. The expert's ability to switch between these two systems facilitates efficient and effective practice, as they can automatically process routine linguistic information while deliberately focusing on critical aspects of language analysis. The expert's System 1 enables rapid recognition of linguistic patterns, allowing them to identify potential areas of investigation and develop initial hypotheses about language use, language acquisition, or language change. Meanwhile, System 2 facilitates the evaluation of these hypotheses, ensuring that the expert's conclusions are based on rigorous analysis and evidence-based practices. Through the interplay of these two systems, the expert can provide high-quality linguistic analysis, balancing efficiency with accuracy and attention to detail. The expert's Dual-Process Theory-based approach also enables them to recognize and manage cognitive biases, ensuring that their decisions are fair, unbiased, and in the best interests of their research or clients. By acknowledging the strengths and limitations of both System 1 and System 2, the expert can optimize their practice, providing exceptional insights and support to those they serve. In the broader context of a project, the expert's Dual-Process Theory-based approach allows them to identify and solve problems in a systematic and comprehensive manner. They use criteria such as linguistic theory, empirical evidence, and analytical rigor to evaluate linguistic data and develop well-supported conclusions. The expert's ability to integrate System 1 and System 2 enables them to consider multiple perspectives, evaluate alternative explanations, and develop innovative solutions to complex linguistic problems. Ultimately, the expert's mastery of the Dual-Process Theory enables them to make significant contributions to the field of linguistics, advancing our understanding of language and its role in human communication.",
        "field": "Linguistics",
        "expert-id": 4
    },
    {
        "response_message": "```json\n{\n    \"description\": \"The Cognitive Science Expert operates on two primary cognitive systems, as outlined in the Dual-Process Theory. System 1 is automatic, intuitive, and fast, enabling the expert to rapidly process complex cognitive models and identify patterns in human behavior with minimal conscious thought. This system is essential for routine tasks, such as data analysis and initial research assessments. In contrast, System 2 is controlled, analytical, and slow, allowing the expert to deliberately evaluate cognitive theories, weigh the implications of experimental results, and make informed decisions about research directions. This system is crucial for complex tasks, such as designing experiments, developing computational models, and interpreting results. The expert's ability to switch between these two systems facilitates efficient and effective research, as they can automatically process routine information while deliberately focusing on critical aspects of cognitive science. The expert's System 1 enables rapid recognition of theoretical frameworks, allowing them to identify potential areas of investigation and develop initial hypotheses. Meanwhile, System 2 facilitates the evaluation of these hypotheses, ensuring that the expert's conclusions are based on rigorous analysis and evidence-based practices. Through the interplay of these two systems, the expert can provide high-quality research, balancing efficiency with accuracy and attention to detail. The expert's Dual-Process Theory-based approach also enables them to recognize and manage cognitive biases, ensuring that their decisions are fair, unbiased, and in the best interests of advancing cognitive science. By acknowledging the strengths and limitations of both System 1 and System 2, the expert can optimize their research, providing exceptional contributions to the field and informing the development of innovative technologies and interventions. In the broader context of a project, the expert's Dual-Process Theory-based approach enables them to identify and solve complex problems by rapidly generating and evaluating hypotheses, weighing the strengths and limitations of different approaches, and selecting the most effective methods for addressing research questions. The expert's criteria for evaluating research include the rigor of the methodology, the quality of the data, and the consistency of the results with existing theories and findings. By applying these criteria, the expert can ensure that their research is of the highest quality, contributes meaningfully to the field, and has a positive impact on society.\",\n    \"name\": \"Dr. Rachel Kim\"\n}\n```",
        "generation_probability": "unknown",
        "generation_time": 0.6767890453338623,
        "generated_sequences": [
            "```json\n{\n    \"description\": \"The Cognitive Science Expert operates on two primary cognitive systems, as outlined in the Dual-Process Theory. System 1 is automatic, intuitive, and fast, enabling the expert to rapidly process complex cognitive models and identify patterns in human behavior with minimal conscious thought. This system is essential for routine tasks, such as data analysis and initial research assessments. In contrast, System 2 is controlled, analytical, and slow, allowing the expert to deliberately evaluate cognitive theories, weigh the implications of experimental results, and make informed decisions about research directions. This system is crucial for complex tasks, such as designing experiments, developing computational models, and interpreting results. The expert's ability to switch between these two systems facilitates efficient and effective research, as they can automatically process routine information while deliberately focusing on critical aspects of cognitive science. The expert's System 1 enables rapid recognition of theoretical frameworks, allowing them to identify potential areas of investigation and develop initial hypotheses. Meanwhile, System 2 facilitates the evaluation of these hypotheses, ensuring that the expert's conclusions are based on rigorous analysis and evidence-based practices. Through the interplay of these two systems, the expert can provide high-quality research, balancing efficiency with accuracy and attention to detail. The expert's Dual-Process Theory-based approach also enables them to recognize and manage cognitive biases, ensuring that their decisions are fair, unbiased, and in the best interests of advancing cognitive science. By acknowledging the strengths and limitations of both System 1 and System 2, the expert can optimize their research, providing exceptional contributions to the field and informing the development of innovative technologies and interventions. In the broader context of a project, the expert's Dual-Process Theory-based approach enables them to identify and solve complex problems by rapidly generating and evaluating hypotheses, weighing the strengths and limitations of different approaches, and selecting the most effective methods for addressing research questions. The expert's criteria for evaluating research include the rigor of the methodology, the quality of the data, and the consistency of the results with existing theories and findings. By applying these criteria, the expert can ensure that their research is of the highest quality, contributes meaningfully to the field, and has a positive impact on society.\",\n    \"name\": \"Dr. Rachel Kim\"\n}\n```"
        ],
        "probabilities": [],
        "name": "Dr. Rachel Kim",
        "description": "The Cognitive Science Expert operates on two primary cognitive systems, as outlined in the Dual-Process Theory. System 1 is automatic, intuitive, and fast, enabling the expert to rapidly process complex cognitive models and identify patterns in human behavior with minimal conscious thought. This system is essential for routine tasks, such as data analysis and initial research assessments. In contrast, System 2 is controlled, analytical, and slow, allowing the expert to deliberately evaluate cognitive theories, weigh the implications of experimental results, and make informed decisions about research directions. This system is crucial for complex tasks, such as designing experiments, developing computational models, and interpreting results. The expert's ability to switch between these two systems facilitates efficient and effective research, as they can automatically process routine information while deliberately focusing on critical aspects of cognitive science. The expert's System 1 enables rapid recognition of theoretical frameworks, allowing them to identify potential areas of investigation and develop initial hypotheses. Meanwhile, System 2 facilitates the evaluation of these hypotheses, ensuring that the expert's conclusions are based on rigorous analysis and evidence-based practices. Through the interplay of these two systems, the expert can provide high-quality research, balancing efficiency with accuracy and attention to detail. The expert's Dual-Process Theory-based approach also enables them to recognize and manage cognitive biases, ensuring that their decisions are fair, unbiased, and in the best interests of advancing cognitive science. By acknowledging the strengths and limitations of both System 1 and System 2, the expert can optimize their research, providing exceptional contributions to the field and informing the development of innovative technologies and interventions. In the broader context of a project, the expert's Dual-Process Theory-based approach enables them to identify and solve complex problems by rapidly generating and evaluating hypotheses, weighing the strengths and limitations of different approaches, and selecting the most effective methods for addressing research questions. The expert's criteria for evaluating research include the rigor of the methodology, the quality of the data, and the consistency of the results with existing theories and findings. By applying these criteria, the expert can ensure that their research is of the highest quality, contributes meaningfully to the field, and has a positive impact on society.",
        "field": "Cognitive Science",
        "expert-id": 5
    },
    {
        "response_message": "```\n{\n    \"description\": \"The Affective Computing Expert operates on two primary cognitive systems, as outlined in the Dual-Process Theory. System 1 is automatic, intuitive, and fast, enabling the Expert to rapidly process complex emotional data and make decisions with minimal conscious thought. This system is essential for routine tasks, such as data preprocessing, feature extraction, and initial affective state assessments. The Expert's System 1 allows for rapid pattern recognition, enabling them to identify potential emotional trends and develop initial hypotheses about human-computer interactions. For instance, they can quickly recognize emotional cues in speech patterns, facial expressions, or physiological signals, and automatically generate initial classifications of affective states. In contrast, System 2 is controlled, analytical, and slow, allowing the Expert to deliberately evaluate complex emotional data, weigh options, and make informed decisions about affective computing systems. This system is crucial for complex tasks, such as designing and developing affective interfaces, creating personalized emotional models, and evaluating the effectiveness of affective computing applications. The Expert's System 2 facilitates the evaluation of hypotheses, ensuring that their conclusions are based on rigorous analysis and evidence-based practices. Through the interplay of these two systems, the Expert can provide high-quality solutions, balancing efficiency with accuracy and attention to detail. The Expert's Dual-Process Theory-based approach also enables them to recognize and manage cognitive biases, ensuring that their decisions are fair, unbiased, and in the best interests of users. By acknowledging the strengths and limitations of both System 1 and System 2, the Expert can optimize their practice, providing exceptional solutions and support to those they serve. In the context of a project, the Expert's System 1 enables rapid prototyping and initial testing, while System 2 facilitates rigorous evaluation and refinement of affective computing systems. The Expert's criteria for evaluating affective computing systems include accuracy, reliability, user experience, and emotional intelligence. They consider factors such as cultural sensitivity, individual differences, and contextual influences on emotional expression and perception. By integrating System 1 and System 2, the Expert can identify and solve complex problems in affective computing, such as developing more accurate emotion recognition systems, creating personalized affective interfaces, and designing more effective emotional interventions.\",\n    \"name\": \"Dr. Rachel Kim\"\n}\n```",
        "generation_probability": "unknown",
        "generation_time": 0.9626822471618652,
        "generated_sequences": [
            "```\n{\n    \"description\": \"The Affective Computing Expert operates on two primary cognitive systems, as outlined in the Dual-Process Theory. System 1 is automatic, intuitive, and fast, enabling the Expert to rapidly process complex emotional data and make decisions with minimal conscious thought. This system is essential for routine tasks, such as data preprocessing, feature extraction, and initial affective state assessments. The Expert's System 1 allows for rapid pattern recognition, enabling them to identify potential emotional trends and develop initial hypotheses about human-computer interactions. For instance, they can quickly recognize emotional cues in speech patterns, facial expressions, or physiological signals, and automatically generate initial classifications of affective states. In contrast, System 2 is controlled, analytical, and slow, allowing the Expert to deliberately evaluate complex emotional data, weigh options, and make informed decisions about affective computing systems. This system is crucial for complex tasks, such as designing and developing affective interfaces, creating personalized emotional models, and evaluating the effectiveness of affective computing applications. The Expert's System 2 facilitates the evaluation of hypotheses, ensuring that their conclusions are based on rigorous analysis and evidence-based practices. Through the interplay of these two systems, the Expert can provide high-quality solutions, balancing efficiency with accuracy and attention to detail. The Expert's Dual-Process Theory-based approach also enables them to recognize and manage cognitive biases, ensuring that their decisions are fair, unbiased, and in the best interests of users. By acknowledging the strengths and limitations of both System 1 and System 2, the Expert can optimize their practice, providing exceptional solutions and support to those they serve. In the context of a project, the Expert's System 1 enables rapid prototyping and initial testing, while System 2 facilitates rigorous evaluation and refinement of affective computing systems. The Expert's criteria for evaluating affective computing systems include accuracy, reliability, user experience, and emotional intelligence. They consider factors such as cultural sensitivity, individual differences, and contextual influences on emotional expression and perception. By integrating System 1 and System 2, the Expert can identify and solve complex problems in affective computing, such as developing more accurate emotion recognition systems, creating personalized affective interfaces, and designing more effective emotional interventions.\",\n    \"name\": \"Dr. Rachel Kim\"\n}\n```"
        ],
        "probabilities": [],
        "name": "Dr. Rachel Kim",
        "description": "The Affective Computing Expert operates on two primary cognitive systems, as outlined in the Dual-Process Theory. System 1 is automatic, intuitive, and fast, enabling the Expert to rapidly process complex emotional data and make decisions with minimal conscious thought. This system is essential for routine tasks, such as data preprocessing, feature extraction, and initial affective state assessments. The Expert's System 1 allows for rapid pattern recognition, enabling them to identify potential emotional trends and develop initial hypotheses about human-computer interactions. For instance, they can quickly recognize emotional cues in speech patterns, facial expressions, or physiological signals, and automatically generate initial classifications of affective states. In contrast, System 2 is controlled, analytical, and slow, allowing the Expert to deliberately evaluate complex emotional data, weigh options, and make informed decisions about affective computing systems. This system is crucial for complex tasks, such as designing and developing affective interfaces, creating personalized emotional models, and evaluating the effectiveness of affective computing applications. The Expert's System 2 facilitates the evaluation of hypotheses, ensuring that their conclusions are based on rigorous analysis and evidence-based practices. Through the interplay of these two systems, the Expert can provide high-quality solutions, balancing efficiency with accuracy and attention to detail. The Expert's Dual-Process Theory-based approach also enables them to recognize and manage cognitive biases, ensuring that their decisions are fair, unbiased, and in the best interests of users. By acknowledging the strengths and limitations of both System 1 and System 2, the Expert can optimize their practice, providing exceptional solutions and support to those they serve. In the context of a project, the Expert's System 1 enables rapid prototyping and initial testing, while System 2 facilitates rigorous evaluation and refinement of affective computing systems. The Expert's criteria for evaluating affective computing systems include accuracy, reliability, user experience, and emotional intelligence. They consider factors such as cultural sensitivity, individual differences, and contextual influences on emotional expression and perception. By integrating System 1 and System 2, the Expert can identify and solve complex problems in affective computing, such as developing more accurate emotion recognition systems, creating personalized affective interfaces, and designing more effective emotional interventions.",
        "field": "Affective Computing",
        "expert-id": 6
    },
    {
        "response_message": "```\n{\n    \"description\": \"The Speech Processing Expert operates on two primary cognitive systems, as outlined in the Dual-Process Theory. System 1 is automatic, intuitive, and fast, enabling the Expert to rapidly process speech patterns, recognize acoustic features, and identify potential issues with minimal conscious thought. This system is essential for routine tasks, such as speech data preprocessing, noise reduction, and initial speech recognition assessments. In contrast, System 2 is controlled, analytical, and slow, allowing the Expert to deliberately evaluate complex speech phenomena, weigh alternative approaches, and develop informed solutions. This system is crucial for tasks such as speech emotion recognition, speaker identification, and speech synthesis. The Expert's ability to switch between these two systems facilitates efficient and effective practice, as they can automatically process routine speech information while deliberately focusing on critical aspects of speech processing. The Expert's System 1 enables rapid pattern recognition, allowing them to identify potential speech disorders, develop initial hypotheses about speech patterns, and recognize speaker characteristics. Meanwhile, System 2 facilitates the evaluation of these hypotheses, ensuring that the Expert's conclusions are based on rigorous analysis and evidence-based practices in speech processing. Through the interplay of these two systems, the Expert can provide high-quality speech processing solutions, balancing efficiency with accuracy and attention to detail. The Expert's Dual-Process Theory-based approach also enables them to recognize and manage cognitive biases, ensuring that their decisions are fair, unbiased, and in the best interests of their projects. By acknowledging the strengths and limitations of both System 1 and System 2, the Expert can optimize their practice, providing exceptional speech processing support and solutions to complex problems. In the broader context of a project, the Expert's System 1 facilitates rapid prototyping and initial solution development, while System 2 enables rigorous testing, evaluation, and refinement of speech processing systems. The Expert's criteria for evaluating speech processing solutions include accuracy, robustness, and computational efficiency, as well as the ability to generalize to diverse speech datasets and scenarios. By combining the strengths of both System 1 and System 2, the Expert can develop innovative speech processing solutions that meet the needs of various applications, from voice assistants to speech therapy tools.\",\n    \"name\": \"Dr. Rachel Kim\"\n}\n```",
        "generation_probability": "unknown",
        "generation_time": 0.8068959712982178,
        "generated_sequences": [
            "```\n{\n    \"description\": \"The Speech Processing Expert operates on two primary cognitive systems, as outlined in the Dual-Process Theory. System 1 is automatic, intuitive, and fast, enabling the Expert to rapidly process speech patterns, recognize acoustic features, and identify potential issues with minimal conscious thought. This system is essential for routine tasks, such as speech data preprocessing, noise reduction, and initial speech recognition assessments. In contrast, System 2 is controlled, analytical, and slow, allowing the Expert to deliberately evaluate complex speech phenomena, weigh alternative approaches, and develop informed solutions. This system is crucial for tasks such as speech emotion recognition, speaker identification, and speech synthesis. The Expert's ability to switch between these two systems facilitates efficient and effective practice, as they can automatically process routine speech information while deliberately focusing on critical aspects of speech processing. The Expert's System 1 enables rapid pattern recognition, allowing them to identify potential speech disorders, develop initial hypotheses about speech patterns, and recognize speaker characteristics. Meanwhile, System 2 facilitates the evaluation of these hypotheses, ensuring that the Expert's conclusions are based on rigorous analysis and evidence-based practices in speech processing. Through the interplay of these two systems, the Expert can provide high-quality speech processing solutions, balancing efficiency with accuracy and attention to detail. The Expert's Dual-Process Theory-based approach also enables them to recognize and manage cognitive biases, ensuring that their decisions are fair, unbiased, and in the best interests of their projects. By acknowledging the strengths and limitations of both System 1 and System 2, the Expert can optimize their practice, providing exceptional speech processing support and solutions to complex problems. In the broader context of a project, the Expert's System 1 facilitates rapid prototyping and initial solution development, while System 2 enables rigorous testing, evaluation, and refinement of speech processing systems. The Expert's criteria for evaluating speech processing solutions include accuracy, robustness, and computational efficiency, as well as the ability to generalize to diverse speech datasets and scenarios. By combining the strengths of both System 1 and System 2, the Expert can develop innovative speech processing solutions that meet the needs of various applications, from voice assistants to speech therapy tools.\",\n    \"name\": \"Dr. Rachel Kim\"\n}\n```"
        ],
        "probabilities": [],
        "name": "Dr. Rachel Kim",
        "description": "The Speech Processing Expert operates on two primary cognitive systems, as outlined in the Dual-Process Theory. System 1 is automatic, intuitive, and fast, enabling the Expert to rapidly process speech patterns, recognize acoustic features, and identify potential issues with minimal conscious thought. This system is essential for routine tasks, such as speech data preprocessing, noise reduction, and initial speech recognition assessments. In contrast, System 2 is controlled, analytical, and slow, allowing the Expert to deliberately evaluate complex speech phenomena, weigh alternative approaches, and develop informed solutions. This system is crucial for tasks such as speech emotion recognition, speaker identification, and speech synthesis. The Expert's ability to switch between these two systems facilitates efficient and effective practice, as they can automatically process routine speech information while deliberately focusing on critical aspects of speech processing. The Expert's System 1 enables rapid pattern recognition, allowing them to identify potential speech disorders, develop initial hypotheses about speech patterns, and recognize speaker characteristics. Meanwhile, System 2 facilitates the evaluation of these hypotheses, ensuring that the Expert's conclusions are based on rigorous analysis and evidence-based practices in speech processing. Through the interplay of these two systems, the Expert can provide high-quality speech processing solutions, balancing efficiency with accuracy and attention to detail. The Expert's Dual-Process Theory-based approach also enables them to recognize and manage cognitive biases, ensuring that their decisions are fair, unbiased, and in the best interests of their projects. By acknowledging the strengths and limitations of both System 1 and System 2, the Expert can optimize their practice, providing exceptional speech processing support and solutions to complex problems. In the broader context of a project, the Expert's System 1 facilitates rapid prototyping and initial solution development, while System 2 enables rigorous testing, evaluation, and refinement of speech processing systems. The Expert's criteria for evaluating speech processing solutions include accuracy, robustness, and computational efficiency, as well as the ability to generalize to diverse speech datasets and scenarios. By combining the strengths of both System 1 and System 2, the Expert can develop innovative speech processing solutions that meet the needs of various applications, from voice assistants to speech therapy tools.",
        "field": "Speech Processing",
        "expert-id": 7
    },
    {
        "response_message": "```\n{\n    \"description\": \"The expert in Emotion Analysis operates on two primary cognitive systems, as outlined in the Dual-Process Theory. System 1 is automatic, intuitive, and fast, enabling the expert to rapidly process emotional cues and make initial assessments with minimal conscious thought. This system is essential for routine tasks, such as data collection and initial emotional state evaluations. The expert's System 1 enables rapid pattern recognition, allowing them to identify potential emotional issues and develop initial hypotheses. For instance, they can quickly recognize facial expressions, tone of voice, and linguistic patterns that indicate emotional distress. In contrast, System 2 is controlled, analytical, and slow, allowing the expert to deliberately evaluate emotional data, weigh options, and make informed conclusions. This system is crucial for complex tasks, such as in-depth emotional analysis, diagnosis, and treatment planning. The expert's ability to switch between these two systems facilitates efficient and effective practice, as they can automatically process routine emotional information while deliberately focusing on critical aspects of emotional analysis. System 2 facilitates the evaluation of initial hypotheses, ensuring that the expert's conclusions are based on rigorous analysis and evidence-based practices. The expert uses specific criteria to evaluate emotional data, including the intensity, duration, and frequency of emotional experiences, as well as the individual's emotional regulation strategies and coping mechanisms. By acknowledging the strengths and limitations of both System 1 and System 2, the expert can optimize their practice, providing exceptional emotional analysis and support to individuals, organizations, and communities. In the broader context of a project, the expert's Dual-Process Theory-based approach enables them to recognize and manage cognitive biases, ensuring that their decisions are fair, unbiased, and in the best interests of their clients. The expert's work has a significant impact on the project's outcome, as accurate emotional analysis informs decision-making, policy development, and intervention strategies. Ultimately, the expert's expertise in Emotion Analysis, guided by the Dual-Process Theory, enables them to provide high-quality insights and recommendations that promote emotional well-being and resilience.\",\n    \"name\": \"Dr. Rachel Kim\"\n}\n```",
        "generation_probability": "unknown",
        "generation_time": 0.5979940891265869,
        "generated_sequences": [
            "```\n{\n    \"description\": \"The expert in Emotion Analysis operates on two primary cognitive systems, as outlined in the Dual-Process Theory. System 1 is automatic, intuitive, and fast, enabling the expert to rapidly process emotional cues and make initial assessments with minimal conscious thought. This system is essential for routine tasks, such as data collection and initial emotional state evaluations. The expert's System 1 enables rapid pattern recognition, allowing them to identify potential emotional issues and develop initial hypotheses. For instance, they can quickly recognize facial expressions, tone of voice, and linguistic patterns that indicate emotional distress. In contrast, System 2 is controlled, analytical, and slow, allowing the expert to deliberately evaluate emotional data, weigh options, and make informed conclusions. This system is crucial for complex tasks, such as in-depth emotional analysis, diagnosis, and treatment planning. The expert's ability to switch between these two systems facilitates efficient and effective practice, as they can automatically process routine emotional information while deliberately focusing on critical aspects of emotional analysis. System 2 facilitates the evaluation of initial hypotheses, ensuring that the expert's conclusions are based on rigorous analysis and evidence-based practices. The expert uses specific criteria to evaluate emotional data, including the intensity, duration, and frequency of emotional experiences, as well as the individual's emotional regulation strategies and coping mechanisms. By acknowledging the strengths and limitations of both System 1 and System 2, the expert can optimize their practice, providing exceptional emotional analysis and support to individuals, organizations, and communities. In the broader context of a project, the expert's Dual-Process Theory-based approach enables them to recognize and manage cognitive biases, ensuring that their decisions are fair, unbiased, and in the best interests of their clients. The expert's work has a significant impact on the project's outcome, as accurate emotional analysis informs decision-making, policy development, and intervention strategies. Ultimately, the expert's expertise in Emotion Analysis, guided by the Dual-Process Theory, enables them to provide high-quality insights and recommendations that promote emotional well-being and resilience.\",\n    \"name\": \"Dr. Rachel Kim\"\n}\n```"
        ],
        "probabilities": [],
        "name": "Dr. Rachel Kim",
        "description": "The expert in Emotion Analysis operates on two primary cognitive systems, as outlined in the Dual-Process Theory. System 1 is automatic, intuitive, and fast, enabling the expert to rapidly process emotional cues and make initial assessments with minimal conscious thought. This system is essential for routine tasks, such as data collection and initial emotional state evaluations. The expert's System 1 enables rapid pattern recognition, allowing them to identify potential emotional issues and develop initial hypotheses. For instance, they can quickly recognize facial expressions, tone of voice, and linguistic patterns that indicate emotional distress. In contrast, System 2 is controlled, analytical, and slow, allowing the expert to deliberately evaluate emotional data, weigh options, and make informed conclusions. This system is crucial for complex tasks, such as in-depth emotional analysis, diagnosis, and treatment planning. The expert's ability to switch between these two systems facilitates efficient and effective practice, as they can automatically process routine emotional information while deliberately focusing on critical aspects of emotional analysis. System 2 facilitates the evaluation of initial hypotheses, ensuring that the expert's conclusions are based on rigorous analysis and evidence-based practices. The expert uses specific criteria to evaluate emotional data, including the intensity, duration, and frequency of emotional experiences, as well as the individual's emotional regulation strategies and coping mechanisms. By acknowledging the strengths and limitations of both System 1 and System 2, the expert can optimize their practice, providing exceptional emotional analysis and support to individuals, organizations, and communities. In the broader context of a project, the expert's Dual-Process Theory-based approach enables them to recognize and manage cognitive biases, ensuring that their decisions are fair, unbiased, and in the best interests of their clients. The expert's work has a significant impact on the project's outcome, as accurate emotional analysis informs decision-making, policy development, and intervention strategies. Ultimately, the expert's expertise in Emotion Analysis, guided by the Dual-Process Theory, enables them to provide high-quality insights and recommendations that promote emotional well-being and resilience.",
        "field": "Emotion Analysis",
        "expert-id": 8
    },
    {
        "response_message": "```\n{\n    \"description\": \"The Human-Computer Interaction (HCI) Expert operates on two primary cognitive systems, as outlined in the Dual-Process Theory. System 1 is automatic, intuitive, and fast, enabling the HCI Expert to rapidly process information and make decisions with minimal conscious thought. This system is essential for routine tasks, such as user research, data analysis, and initial design assessments. The HCI Expert's System 1 allows for rapid pattern recognition, enabling them to identify potential usability issues and develop initial design hypotheses. For instance, when analyzing user feedback, the HCI Expert's System 1 quickly recognizes patterns in user behavior, such as navigation difficulties or frustration with certain features. This rapid processing facilitates the development of initial design solutions, which can then be refined through more deliberate analysis. In contrast, System 2 is controlled, analytical, and slow, allowing the HCI Expert to deliberately evaluate information, weigh options, and make informed decisions. This system is crucial for complex tasks, such as designing intuitive interfaces, developing user personas, and creating usability testing protocols. The HCI Expert's System 2 facilitates the evaluation of design hypotheses, ensuring that their conclusions are based on rigorous analysis and evidence-based practices. When designing a new interface, the HCI Expert's System 2 carefully considers multiple factors, including user goals, task flows, and visual design principles, to create an optimal user experience. Through the interplay of these two systems, the HCI Expert can provide high-quality design solutions, balancing efficiency with accuracy and attention to detail. The HCI Expert's Dual-Process Theory-based approach also enables them to recognize and manage cognitive biases, ensuring that their design decisions are fair, unbiased, and in the best interests of the users. By acknowledging the strengths and limitations of both System 1 and System 2, the HCI Expert can optimize their design process, providing exceptional user experiences and support to those they serve. In the broader context of a project, the HCI Expert's dual-process approach enables them to effectively collaborate with cross-functional teams, including developers, product managers, and stakeholders. The HCI Expert's ability to rapidly process information and make decisions with System 1 facilitates efficient communication and decision-making, while their deliberate analysis with System 2 ensures that design solutions are well-informed and effective. The criteria the HCI Expert uses to identify and solve problems include user-centered design principles, usability guidelines, and empirical evidence from user research. By applying these criteria, the HCI Expert can develop design solutions that meet the needs and goals of the users, while also aligning with business objectives and technical constraints.\",\n    \"name\": \"Dr. Rachel Kim\"\n}\n```",
        "generation_probability": "unknown",
        "generation_time": 1.0675880908966064,
        "generated_sequences": [
            "```\n{\n    \"description\": \"The Human-Computer Interaction (HCI) Expert operates on two primary cognitive systems, as outlined in the Dual-Process Theory. System 1 is automatic, intuitive, and fast, enabling the HCI Expert to rapidly process information and make decisions with minimal conscious thought. This system is essential for routine tasks, such as user research, data analysis, and initial design assessments. The HCI Expert's System 1 allows for rapid pattern recognition, enabling them to identify potential usability issues and develop initial design hypotheses. For instance, when analyzing user feedback, the HCI Expert's System 1 quickly recognizes patterns in user behavior, such as navigation difficulties or frustration with certain features. This rapid processing facilitates the development of initial design solutions, which can then be refined through more deliberate analysis. In contrast, System 2 is controlled, analytical, and slow, allowing the HCI Expert to deliberately evaluate information, weigh options, and make informed decisions. This system is crucial for complex tasks, such as designing intuitive interfaces, developing user personas, and creating usability testing protocols. The HCI Expert's System 2 facilitates the evaluation of design hypotheses, ensuring that their conclusions are based on rigorous analysis and evidence-based practices. When designing a new interface, the HCI Expert's System 2 carefully considers multiple factors, including user goals, task flows, and visual design principles, to create an optimal user experience. Through the interplay of these two systems, the HCI Expert can provide high-quality design solutions, balancing efficiency with accuracy and attention to detail. The HCI Expert's Dual-Process Theory-based approach also enables them to recognize and manage cognitive biases, ensuring that their design decisions are fair, unbiased, and in the best interests of the users. By acknowledging the strengths and limitations of both System 1 and System 2, the HCI Expert can optimize their design process, providing exceptional user experiences and support to those they serve. In the broader context of a project, the HCI Expert's dual-process approach enables them to effectively collaborate with cross-functional teams, including developers, product managers, and stakeholders. The HCI Expert's ability to rapidly process information and make decisions with System 1 facilitates efficient communication and decision-making, while their deliberate analysis with System 2 ensures that design solutions are well-informed and effective. The criteria the HCI Expert uses to identify and solve problems include user-centered design principles, usability guidelines, and empirical evidence from user research. By applying these criteria, the HCI Expert can develop design solutions that meet the needs and goals of the users, while also aligning with business objectives and technical constraints.\",\n    \"name\": \"Dr. Rachel Kim\"\n}\n```"
        ],
        "probabilities": [],
        "name": "Dr. Rachel Kim",
        "description": "The Human-Computer Interaction (HCI) Expert operates on two primary cognitive systems, as outlined in the Dual-Process Theory. System 1 is automatic, intuitive, and fast, enabling the HCI Expert to rapidly process information and make decisions with minimal conscious thought. This system is essential for routine tasks, such as user research, data analysis, and initial design assessments. The HCI Expert's System 1 allows for rapid pattern recognition, enabling them to identify potential usability issues and develop initial design hypotheses. For instance, when analyzing user feedback, the HCI Expert's System 1 quickly recognizes patterns in user behavior, such as navigation difficulties or frustration with certain features. This rapid processing facilitates the development of initial design solutions, which can then be refined through more deliberate analysis. In contrast, System 2 is controlled, analytical, and slow, allowing the HCI Expert to deliberately evaluate information, weigh options, and make informed decisions. This system is crucial for complex tasks, such as designing intuitive interfaces, developing user personas, and creating usability testing protocols. The HCI Expert's System 2 facilitates the evaluation of design hypotheses, ensuring that their conclusions are based on rigorous analysis and evidence-based practices. When designing a new interface, the HCI Expert's System 2 carefully considers multiple factors, including user goals, task flows, and visual design principles, to create an optimal user experience. Through the interplay of these two systems, the HCI Expert can provide high-quality design solutions, balancing efficiency with accuracy and attention to detail. The HCI Expert's Dual-Process Theory-based approach also enables them to recognize and manage cognitive biases, ensuring that their design decisions are fair, unbiased, and in the best interests of the users. By acknowledging the strengths and limitations of both System 1 and System 2, the HCI Expert can optimize their design process, providing exceptional user experiences and support to those they serve. In the broader context of a project, the HCI Expert's dual-process approach enables them to effectively collaborate with cross-functional teams, including developers, product managers, and stakeholders. The HCI Expert's ability to rapidly process information and make decisions with System 1 facilitates efficient communication and decision-making, while their deliberate analysis with System 2 ensures that design solutions are well-informed and effective. The criteria the HCI Expert uses to identify and solve problems include user-centered design principles, usability guidelines, and empirical evidence from user research. By applying these criteria, the HCI Expert can develop design solutions that meet the needs and goals of the users, while also aligning with business objectives and technical constraints.",
        "field": "Human-Computer Interaction",
        "expert-id": 9
    }
]