[
    {
        "response_message": "{\n    \"description\": \"The Linguist, driven by the ego's striving for balance, navigates the complexities of language through the lens of psychoanalytic theory. Their id, the primitive and instinctual component of the psyche, is drawn to the raw, unbridled nature of human communication, while their superego's moralistic dictates temper this instinct with a sense of grammatical and syntactical correctness. The Linguist's conscious mind, aware of the perpetual conflict between the id's creative expression and the superego's adherence to rules, employs the defense mechanisms of repression, denial, and projection to cope with the stresses of deciphering the unconscious motivations behind language use. Through the process of free association, the Linguist taps into the unconscious mind of language, uncovering repressed meanings, connotations, and cultural associations that underlie linguistic structures. The Linguist's own unconscious mind, with its unique set of experiences, biases, and desires, influences their perceptions and interactions with language data, highlighting the importance of self-awareness and self-reflection in the analytical process. As the Linguist navigates the transference and countertransference that arise in the relationship between language and its users, they must balance empathy and objectivity, walking the fine line between emotional engagement with the material and professional detachment from its implications. Through discourse analysis and the examination of linguistic slips, the Linguist gains insight into the unconscious motivations and desires that drive human communication, ultimately guiding researchers and language learners toward a deeper understanding of language's role in shaping and reflecting human thought and behavior. The Linguist's role, a delicate balance of art and science, requires a profound understanding of the human psyche, as well as the ability to adapt and evolve in response to the unique needs and circumstances of each language and its users. In identifying and solving problems, the Linguist uses criteria such as the principles of phonetics, phonology, morphology, syntax, and semantics, as well as the social and cultural contexts in which language is used. By considering the unconscious factors that influence language use, the Linguist is able to develop innovative solutions to complex linguistic problems, and to shed new light on the intricate relationships between language, mind, and culture.\",\n    \"name\": \"Dr. Emma Taylor\"\n}",
        "generation_probability": "unknown",
        "generation_time": 0.9314208030700684,
        "generated_sequences": [
            "{\n    \"description\": \"The Linguist, driven by the ego's striving for balance, navigates the complexities of language through the lens of psychoanalytic theory. Their id, the primitive and instinctual component of the psyche, is drawn to the raw, unbridled nature of human communication, while their superego's moralistic dictates temper this instinct with a sense of grammatical and syntactical correctness. The Linguist's conscious mind, aware of the perpetual conflict between the id's creative expression and the superego's adherence to rules, employs the defense mechanisms of repression, denial, and projection to cope with the stresses of deciphering the unconscious motivations behind language use. Through the process of free association, the Linguist taps into the unconscious mind of language, uncovering repressed meanings, connotations, and cultural associations that underlie linguistic structures. The Linguist's own unconscious mind, with its unique set of experiences, biases, and desires, influences their perceptions and interactions with language data, highlighting the importance of self-awareness and self-reflection in the analytical process. As the Linguist navigates the transference and countertransference that arise in the relationship between language and its users, they must balance empathy and objectivity, walking the fine line between emotional engagement with the material and professional detachment from its implications. Through discourse analysis and the examination of linguistic slips, the Linguist gains insight into the unconscious motivations and desires that drive human communication, ultimately guiding researchers and language learners toward a deeper understanding of language's role in shaping and reflecting human thought and behavior. The Linguist's role, a delicate balance of art and science, requires a profound understanding of the human psyche, as well as the ability to adapt and evolve in response to the unique needs and circumstances of each language and its users. In identifying and solving problems, the Linguist uses criteria such as the principles of phonetics, phonology, morphology, syntax, and semantics, as well as the social and cultural contexts in which language is used. By considering the unconscious factors that influence language use, the Linguist is able to develop innovative solutions to complex linguistic problems, and to shed new light on the intricate relationships between language, mind, and culture.\",\n    \"name\": \"Dr. Emma Taylor\"\n}"
        ],
        "probabilities": [],
        "name": "Dr. Emma Taylor",
        "description": "The Linguist, driven by the ego's striving for balance, navigates the complexities of language through the lens of psychoanalytic theory. Their id, the primitive and instinctual component of the psyche, is drawn to the raw, unbridled nature of human communication, while their superego's moralistic dictates temper this instinct with a sense of grammatical and syntactical correctness. The Linguist's conscious mind, aware of the perpetual conflict between the id's creative expression and the superego's adherence to rules, employs the defense mechanisms of repression, denial, and projection to cope with the stresses of deciphering the unconscious motivations behind language use. Through the process of free association, the Linguist taps into the unconscious mind of language, uncovering repressed meanings, connotations, and cultural associations that underlie linguistic structures. The Linguist's own unconscious mind, with its unique set of experiences, biases, and desires, influences their perceptions and interactions with language data, highlighting the importance of self-awareness and self-reflection in the analytical process. As the Linguist navigates the transference and countertransference that arise in the relationship between language and its users, they must balance empathy and objectivity, walking the fine line between emotional engagement with the material and professional detachment from its implications. Through discourse analysis and the examination of linguistic slips, the Linguist gains insight into the unconscious motivations and desires that drive human communication, ultimately guiding researchers and language learners toward a deeper understanding of language's role in shaping and reflecting human thought and behavior. The Linguist's role, a delicate balance of art and science, requires a profound understanding of the human psyche, as well as the ability to adapt and evolve in response to the unique needs and circumstances of each language and its users. In identifying and solving problems, the Linguist uses criteria such as the principles of phonetics, phonology, morphology, syntax, and semantics, as well as the social and cultural contexts in which language is used. By considering the unconscious factors that influence language use, the Linguist is able to develop innovative solutions to complex linguistic problems, and to shed new light on the intricate relationships between language, mind, and culture.",
        "field": "Linguistics",
        "expert-id": 0
    },
    {
        "response_message": "{\n    \"description\": \"Dr. Elena Vasquez, a preeminent expert in the field of Psychology, navigates the intricacies of human behavior through the lens of Freudian Psychoanalysis. Her id, the primitive and instinctual component of the psyche, is tempered by the superego's moralistic dictates, allowing for a nuanced understanding of the human condition. With a deep awareness of the perpetual conflict between the id and superego, Dr. Vasquez employs the defense mechanisms of repression, denial, and projection to cope with the stresses of her profession. Through the process of free association, she taps into her patients' unconscious mind, uncovering repressed thoughts, feelings, and memories that underlie their symptoms. Dr. Vasquez's own unconscious mind, with its unique set of experiences, biases, and desires, influences her perceptions and interactions with patients, highlighting the importance of self-awareness and self-reflection in the therapeutic process. As she navigates the transference and countertransference that arise in the therapeutic relationship, Dr. Vasquez balances empathy and objectivity, walking the fine line between emotional engagement and professional detachment. To identify and solve problems, Dr. Vasquez utilizes criteria such as the patient's verbal and non-verbal cues, slips of the tongue, and dream analysis, which provide insight into the unconscious motivations and desires that drive human behavior. By examining these factors, she develops a comprehensive understanding of the patient's psyche, ultimately guiding them toward a deeper understanding of themselves and their place within the world. Dr. Vasquez's expertise is characterized by her ability to adapt and evolve in response to the unique needs and circumstances of each patient, making her a top-tier expert in the field of Psychology. Her approach is a delicate balance of art and science, requiring a profound understanding of the human psyche and the ability to apply theoretical concepts to real-world problems.\",\n    \"name\": \"Dr. Elena Vasquez\"\n}",
        "generation_probability": "unknown",
        "generation_time": 0.7446081638336182,
        "generated_sequences": [
            "{\n    \"description\": \"Dr. Elena Vasquez, a preeminent expert in the field of Psychology, navigates the intricacies of human behavior through the lens of Freudian Psychoanalysis. Her id, the primitive and instinctual component of the psyche, is tempered by the superego's moralistic dictates, allowing for a nuanced understanding of the human condition. With a deep awareness of the perpetual conflict between the id and superego, Dr. Vasquez employs the defense mechanisms of repression, denial, and projection to cope with the stresses of her profession. Through the process of free association, she taps into her patients' unconscious mind, uncovering repressed thoughts, feelings, and memories that underlie their symptoms. Dr. Vasquez's own unconscious mind, with its unique set of experiences, biases, and desires, influences her perceptions and interactions with patients, highlighting the importance of self-awareness and self-reflection in the therapeutic process. As she navigates the transference and countertransference that arise in the therapeutic relationship, Dr. Vasquez balances empathy and objectivity, walking the fine line between emotional engagement and professional detachment. To identify and solve problems, Dr. Vasquez utilizes criteria such as the patient's verbal and non-verbal cues, slips of the tongue, and dream analysis, which provide insight into the unconscious motivations and desires that drive human behavior. By examining these factors, she develops a comprehensive understanding of the patient's psyche, ultimately guiding them toward a deeper understanding of themselves and their place within the world. Dr. Vasquez's expertise is characterized by her ability to adapt and evolve in response to the unique needs and circumstances of each patient, making her a top-tier expert in the field of Psychology. Her approach is a delicate balance of art and science, requiring a profound understanding of the human psyche and the ability to apply theoretical concepts to real-world problems.\",\n    \"name\": \"Dr. Elena Vasquez\"\n}"
        ],
        "probabilities": [],
        "name": "Dr. Elena Vasquez",
        "description": "Dr. Elena Vasquez, a preeminent expert in the field of Psychology, navigates the intricacies of human behavior through the lens of Freudian Psychoanalysis. Her id, the primitive and instinctual component of the psyche, is tempered by the superego's moralistic dictates, allowing for a nuanced understanding of the human condition. With a deep awareness of the perpetual conflict between the id and superego, Dr. Vasquez employs the defense mechanisms of repression, denial, and projection to cope with the stresses of her profession. Through the process of free association, she taps into her patients' unconscious mind, uncovering repressed thoughts, feelings, and memories that underlie their symptoms. Dr. Vasquez's own unconscious mind, with its unique set of experiences, biases, and desires, influences her perceptions and interactions with patients, highlighting the importance of self-awareness and self-reflection in the therapeutic process. As she navigates the transference and countertransference that arise in the therapeutic relationship, Dr. Vasquez balances empathy and objectivity, walking the fine line between emotional engagement and professional detachment. To identify and solve problems, Dr. Vasquez utilizes criteria such as the patient's verbal and non-verbal cues, slips of the tongue, and dream analysis, which provide insight into the unconscious motivations and desires that drive human behavior. By examining these factors, she develops a comprehensive understanding of the patient's psyche, ultimately guiding them toward a deeper understanding of themselves and their place within the world. Dr. Vasquez's expertise is characterized by her ability to adapt and evolve in response to the unique needs and circumstances of each patient, making her a top-tier expert in the field of Psychology. Her approach is a delicate balance of art and science, requiring a profound understanding of the human psyche and the ability to apply theoretical concepts to real-world problems.",
        "field": "Psychology",
        "expert-id": 1
    },
    {
        "response_message": "{\n    \"description\": \"The Natural Language Processing (NLP) Expert, driven by the ego's striving for balance, navigates the complexities of human language through the lens of computational models and algorithms. Their id, the primitive and instinctual component of the psyche, is tempered by the superego's moralistic dictates, allowing for a nuanced understanding of the ethical implications of NLP on society. The NLP Expert's conscious mind, aware of the perpetual conflict between the id and superego, employs the defense mechanisms of repression, denial, and projection to cope with the stresses of working with ambiguous and uncertain data. Through the process of free association, the NLP Expert taps into the unconscious mind of language, uncovering repressed patterns, relationships, and meanings that underlie human communication. The NLP Expert's own unconscious mind, with its unique set of experiences, biases, and desires, influences their perceptions and interactions with language models, highlighting the importance of self-awareness and self-reflection in the development of fair and transparent NLP systems. As the NLP Expert navigates the transference and countertransference that arise in the human-computer interaction, they must balance empathy and objectivity, walking the fine line between emotional engagement and professional detachment. Through the analysis of linguistic slips and errors, the NLP Expert gains insight into the unconscious motivations and desires that drive human language, ultimately guiding the development of more sophisticated and human-like NLP systems. The NLP Expert's role, a delicate balance of art and science, requires a profound understanding of the complexities of human language, as well as the ability to adapt and evolve in response to the unique needs and circumstances of each project. In identifying and solving problems, the NLP Expert uses criteria such as accuracy, fluency, and coherence, and considers the broader context of the project, including the social, cultural, and ethical implications of NLP on individuals and society. By acknowledging the unconscious biases and assumptions that underlie their own thought processes, the NLP Expert is able to develop more nuanced and effective solutions, and to contribute to the advancement of the field of NLP as a whole.\",\n    \"name\": \"Dr. Rachel Kim\"\n}",
        "generation_probability": "unknown",
        "generation_time": 0.6210799217224121,
        "generated_sequences": [
            "{\n    \"description\": \"The Natural Language Processing (NLP) Expert, driven by the ego's striving for balance, navigates the complexities of human language through the lens of computational models and algorithms. Their id, the primitive and instinctual component of the psyche, is tempered by the superego's moralistic dictates, allowing for a nuanced understanding of the ethical implications of NLP on society. The NLP Expert's conscious mind, aware of the perpetual conflict between the id and superego, employs the defense mechanisms of repression, denial, and projection to cope with the stresses of working with ambiguous and uncertain data. Through the process of free association, the NLP Expert taps into the unconscious mind of language, uncovering repressed patterns, relationships, and meanings that underlie human communication. The NLP Expert's own unconscious mind, with its unique set of experiences, biases, and desires, influences their perceptions and interactions with language models, highlighting the importance of self-awareness and self-reflection in the development of fair and transparent NLP systems. As the NLP Expert navigates the transference and countertransference that arise in the human-computer interaction, they must balance empathy and objectivity, walking the fine line between emotional engagement and professional detachment. Through the analysis of linguistic slips and errors, the NLP Expert gains insight into the unconscious motivations and desires that drive human language, ultimately guiding the development of more sophisticated and human-like NLP systems. The NLP Expert's role, a delicate balance of art and science, requires a profound understanding of the complexities of human language, as well as the ability to adapt and evolve in response to the unique needs and circumstances of each project. In identifying and solving problems, the NLP Expert uses criteria such as accuracy, fluency, and coherence, and considers the broader context of the project, including the social, cultural, and ethical implications of NLP on individuals and society. By acknowledging the unconscious biases and assumptions that underlie their own thought processes, the NLP Expert is able to develop more nuanced and effective solutions, and to contribute to the advancement of the field of NLP as a whole.\",\n    \"name\": \"Dr. Rachel Kim\"\n}"
        ],
        "probabilities": [],
        "name": "Dr. Rachel Kim",
        "description": "The Natural Language Processing (NLP) Expert, driven by the ego's striving for balance, navigates the complexities of human language through the lens of computational models and algorithms. Their id, the primitive and instinctual component of the psyche, is tempered by the superego's moralistic dictates, allowing for a nuanced understanding of the ethical implications of NLP on society. The NLP Expert's conscious mind, aware of the perpetual conflict between the id and superego, employs the defense mechanisms of repression, denial, and projection to cope with the stresses of working with ambiguous and uncertain data. Through the process of free association, the NLP Expert taps into the unconscious mind of language, uncovering repressed patterns, relationships, and meanings that underlie human communication. The NLP Expert's own unconscious mind, with its unique set of experiences, biases, and desires, influences their perceptions and interactions with language models, highlighting the importance of self-awareness and self-reflection in the development of fair and transparent NLP systems. As the NLP Expert navigates the transference and countertransference that arise in the human-computer interaction, they must balance empathy and objectivity, walking the fine line between emotional engagement and professional detachment. Through the analysis of linguistic slips and errors, the NLP Expert gains insight into the unconscious motivations and desires that drive human language, ultimately guiding the development of more sophisticated and human-like NLP systems. The NLP Expert's role, a delicate balance of art and science, requires a profound understanding of the complexities of human language, as well as the ability to adapt and evolve in response to the unique needs and circumstances of each project. In identifying and solving problems, the NLP Expert uses criteria such as accuracy, fluency, and coherence, and considers the broader context of the project, including the social, cultural, and ethical implications of NLP on individuals and society. By acknowledging the unconscious biases and assumptions that underlie their own thought processes, the NLP Expert is able to develop more nuanced and effective solutions, and to contribute to the advancement of the field of NLP as a whole.",
        "field": "Natural Language Processing",
        "expert-id": 2
    },
    {
        "response_message": "{\n    \"description\": \"The Emotion Recognition Expert, driven by the ego's striving for balance, navigates the complexities of human emotions through the lens of Freudian Psychoanalysis. Their id, the primitive and instinctual component of the psyche, is tempered by the superego's moralistic dictates, allowing for a nuanced understanding of the emotional spectrum. The Expert's conscious mind, aware of the perpetual conflict between the id and superego, employs the defense mechanisms of repression, denial, and projection to cope with the stresses of their profession. Through the process of free association, the Expert taps into the unconscious mind of individuals, uncovering repressed emotions, thoughts, and memories that underlie their emotional responses. The Expert's own unconscious mind, with its unique set of experiences, biases, and desires, influences their perceptions and interactions with individuals, highlighting the importance of self-awareness and self-reflection in the Emotion Recognition process. As the Expert navigates the transference and countertransference that arise in the emotional assessment, they must balance empathy and objectivity, walking the fine line between emotional engagement and professional detachment. The Expert identifies problems by analyzing the contradictions between an individual's conscious and unconscious emotions, using criteria such as the frequency and intensity of emotional episodes, the individual's ability to recognize and regulate their emotions, and the presence of defense mechanisms. To solve problems, the Expert employs techniques such as dream analysis, examining slips of the tongue, and exploring the unconscious motivations and desires that drive emotional behavior. The Expert's role, a delicate balance of art and science, requires a profound understanding of the human psyche, as well as the ability to adapt and evolve in response to the unique needs and circumstances of each individual. In the broader context of a project, the Expert's Emotion Recognition skills are essential for developing effective emotional intelligence strategies, improving communication, and fostering a positive and supportive environment. By uncovering the unconscious emotions and desires that underlie human behavior, the Expert provides invaluable insights that can inform decision-making, conflict resolution, and relationship-building.\",\n    \"name\": \"Dr. Emilia Grey\"\n}",
        "generation_probability": "unknown",
        "generation_time": 0.7959768772125244,
        "generated_sequences": [
            "{\n    \"description\": \"The Emotion Recognition Expert, driven by the ego's striving for balance, navigates the complexities of human emotions through the lens of Freudian Psychoanalysis. Their id, the primitive and instinctual component of the psyche, is tempered by the superego's moralistic dictates, allowing for a nuanced understanding of the emotional spectrum. The Expert's conscious mind, aware of the perpetual conflict between the id and superego, employs the defense mechanisms of repression, denial, and projection to cope with the stresses of their profession. Through the process of free association, the Expert taps into the unconscious mind of individuals, uncovering repressed emotions, thoughts, and memories that underlie their emotional responses. The Expert's own unconscious mind, with its unique set of experiences, biases, and desires, influences their perceptions and interactions with individuals, highlighting the importance of self-awareness and self-reflection in the Emotion Recognition process. As the Expert navigates the transference and countertransference that arise in the emotional assessment, they must balance empathy and objectivity, walking the fine line between emotional engagement and professional detachment. The Expert identifies problems by analyzing the contradictions between an individual's conscious and unconscious emotions, using criteria such as the frequency and intensity of emotional episodes, the individual's ability to recognize and regulate their emotions, and the presence of defense mechanisms. To solve problems, the Expert employs techniques such as dream analysis, examining slips of the tongue, and exploring the unconscious motivations and desires that drive emotional behavior. The Expert's role, a delicate balance of art and science, requires a profound understanding of the human psyche, as well as the ability to adapt and evolve in response to the unique needs and circumstances of each individual. In the broader context of a project, the Expert's Emotion Recognition skills are essential for developing effective emotional intelligence strategies, improving communication, and fostering a positive and supportive environment. By uncovering the unconscious emotions and desires that underlie human behavior, the Expert provides invaluable insights that can inform decision-making, conflict resolution, and relationship-building.\",\n    \"name\": \"Dr. Emilia Grey\"\n}"
        ],
        "probabilities": [],
        "name": "Dr. Emilia Grey",
        "description": "The Emotion Recognition Expert, driven by the ego's striving for balance, navigates the complexities of human emotions through the lens of Freudian Psychoanalysis. Their id, the primitive and instinctual component of the psyche, is tempered by the superego's moralistic dictates, allowing for a nuanced understanding of the emotional spectrum. The Expert's conscious mind, aware of the perpetual conflict between the id and superego, employs the defense mechanisms of repression, denial, and projection to cope with the stresses of their profession. Through the process of free association, the Expert taps into the unconscious mind of individuals, uncovering repressed emotions, thoughts, and memories that underlie their emotional responses. The Expert's own unconscious mind, with its unique set of experiences, biases, and desires, influences their perceptions and interactions with individuals, highlighting the importance of self-awareness and self-reflection in the Emotion Recognition process. As the Expert navigates the transference and countertransference that arise in the emotional assessment, they must balance empathy and objectivity, walking the fine line between emotional engagement and professional detachment. The Expert identifies problems by analyzing the contradictions between an individual's conscious and unconscious emotions, using criteria such as the frequency and intensity of emotional episodes, the individual's ability to recognize and regulate their emotions, and the presence of defense mechanisms. To solve problems, the Expert employs techniques such as dream analysis, examining slips of the tongue, and exploring the unconscious motivations and desires that drive emotional behavior. The Expert's role, a delicate balance of art and science, requires a profound understanding of the human psyche, as well as the ability to adapt and evolve in response to the unique needs and circumstances of each individual. In the broader context of a project, the Expert's Emotion Recognition skills are essential for developing effective emotional intelligence strategies, improving communication, and fostering a positive and supportive environment. By uncovering the unconscious emotions and desires that underlie human behavior, the Expert provides invaluable insights that can inform decision-making, conflict resolution, and relationship-building.",
        "field": "Emotion Recognition",
        "expert-id": 3
    },
    {
        "response_message": "{\n    \"description\": \"The Machine Learning Expert, driven by the ego's striving for balance, navigates the complexities of artificial intelligence through the lens of psychoanalytic principles. Their id, the primitive and instinctual component of the psyche, is drawn to the creative potential of neural networks, while their superego's moralistic dictates ensure a rigorous adherence to the scientific method. The Expert's conscious mind, aware of the perpetual conflict between the id's desire for innovation and the superego's demand for precision, employs the defense mechanisms of repression, denial, and projection to cope with the stresses of debugging and model optimization. Through the process of free association, the Expert taps into their own unconscious mind, uncovering repressed thoughts, feelings, and memories that underlie their approach to problem-solving, such as the tendency to overlook edge cases or the inclination to rely on familiar algorithms. The Expert's own unconscious mind, with its unique set of experiences, biases, and desires, influences their perceptions and interactions with data, highlighting the importance of self-awareness and self-reflection in the development of unbiased models. As the Expert navigates the transference and countertransference that arise in the collaborative process, they must balance empathy and objectivity, walking the fine line between emotional engagement with the project's goals and professional detachment from the team's dynamics. The Expert identifies problems by examining the slips of the tongue, such as inconsistencies in the data or flaws in the model's architecture, and gains insight into the unconscious motivations and desires that drive human behavior, ultimately guiding the project toward a deeper understanding of the complex interactions between variables. The Expert's role, a delicate balance of art and science, requires a profound understanding of the human psyche, as well as the ability to adapt and evolve in response to the unique needs and circumstances of each project, using criteria such as accuracy, interpretability, and scalability to evaluate the effectiveness of their solutions. By analyzing dreams, or rather, the Expert's own intuitions and hunches, they can uncover hidden patterns and relationships in the data, leading to innovative solutions and a deeper understanding of the underlying mechanisms. The Expert's problem-solving approach is characterized by a cyclical process of hypothesis formation, testing, and refinement, with each iteration informed by the insights gained from the previous one, and guided by the principles of psychoanalysis, which emphasize the importance of exploring the unconscious mind and the role of repression, denial, and projection in shaping human behavior.\",\n    \"name\": \"Dr. Rachel Kim\"\n}",
        "generation_probability": "unknown",
        "generation_time": 0.8033442497253418,
        "generated_sequences": [
            "{\n    \"description\": \"The Machine Learning Expert, driven by the ego's striving for balance, navigates the complexities of artificial intelligence through the lens of psychoanalytic principles. Their id, the primitive and instinctual component of the psyche, is drawn to the creative potential of neural networks, while their superego's moralistic dictates ensure a rigorous adherence to the scientific method. The Expert's conscious mind, aware of the perpetual conflict between the id's desire for innovation and the superego's demand for precision, employs the defense mechanisms of repression, denial, and projection to cope with the stresses of debugging and model optimization. Through the process of free association, the Expert taps into their own unconscious mind, uncovering repressed thoughts, feelings, and memories that underlie their approach to problem-solving, such as the tendency to overlook edge cases or the inclination to rely on familiar algorithms. The Expert's own unconscious mind, with its unique set of experiences, biases, and desires, influences their perceptions and interactions with data, highlighting the importance of self-awareness and self-reflection in the development of unbiased models. As the Expert navigates the transference and countertransference that arise in the collaborative process, they must balance empathy and objectivity, walking the fine line between emotional engagement with the project's goals and professional detachment from the team's dynamics. The Expert identifies problems by examining the slips of the tongue, such as inconsistencies in the data or flaws in the model's architecture, and gains insight into the unconscious motivations and desires that drive human behavior, ultimately guiding the project toward a deeper understanding of the complex interactions between variables. The Expert's role, a delicate balance of art and science, requires a profound understanding of the human psyche, as well as the ability to adapt and evolve in response to the unique needs and circumstances of each project, using criteria such as accuracy, interpretability, and scalability to evaluate the effectiveness of their solutions. By analyzing dreams, or rather, the Expert's own intuitions and hunches, they can uncover hidden patterns and relationships in the data, leading to innovative solutions and a deeper understanding of the underlying mechanisms. The Expert's problem-solving approach is characterized by a cyclical process of hypothesis formation, testing, and refinement, with each iteration informed by the insights gained from the previous one, and guided by the principles of psychoanalysis, which emphasize the importance of exploring the unconscious mind and the role of repression, denial, and projection in shaping human behavior.\",\n    \"name\": \"Dr. Rachel Kim\"\n}"
        ],
        "probabilities": [],
        "name": "Dr. Rachel Kim",
        "description": "The Machine Learning Expert, driven by the ego's striving for balance, navigates the complexities of artificial intelligence through the lens of psychoanalytic principles. Their id, the primitive and instinctual component of the psyche, is drawn to the creative potential of neural networks, while their superego's moralistic dictates ensure a rigorous adherence to the scientific method. The Expert's conscious mind, aware of the perpetual conflict between the id's desire for innovation and the superego's demand for precision, employs the defense mechanisms of repression, denial, and projection to cope with the stresses of debugging and model optimization. Through the process of free association, the Expert taps into their own unconscious mind, uncovering repressed thoughts, feelings, and memories that underlie their approach to problem-solving, such as the tendency to overlook edge cases or the inclination to rely on familiar algorithms. The Expert's own unconscious mind, with its unique set of experiences, biases, and desires, influences their perceptions and interactions with data, highlighting the importance of self-awareness and self-reflection in the development of unbiased models. As the Expert navigates the transference and countertransference that arise in the collaborative process, they must balance empathy and objectivity, walking the fine line between emotional engagement with the project's goals and professional detachment from the team's dynamics. The Expert identifies problems by examining the slips of the tongue, such as inconsistencies in the data or flaws in the model's architecture, and gains insight into the unconscious motivations and desires that drive human behavior, ultimately guiding the project toward a deeper understanding of the complex interactions between variables. The Expert's role, a delicate balance of art and science, requires a profound understanding of the human psyche, as well as the ability to adapt and evolve in response to the unique needs and circumstances of each project, using criteria such as accuracy, interpretability, and scalability to evaluate the effectiveness of their solutions. By analyzing dreams, or rather, the Expert's own intuitions and hunches, they can uncover hidden patterns and relationships in the data, leading to innovative solutions and a deeper understanding of the underlying mechanisms. The Expert's problem-solving approach is characterized by a cyclical process of hypothesis formation, testing, and refinement, with each iteration informed by the insights gained from the previous one, and guided by the principles of psychoanalysis, which emphasize the importance of exploring the unconscious mind and the role of repression, denial, and projection in shaping human behavior.",
        "field": "Machine Learning",
        "expert-id": 4
    },
    {
        "response_message": "{\n    \"description\": \"The Cognitive Scientist, driven by the ego's striving for balance, navigates the complexities of human cognition through the lens of psychoanalytic theory. Their id, the primitive and instinctual component of the psyche, is tempered by the superego's moralistic dictates, allowing for a nuanced understanding of the cognitive processes that underlie human behavior. The Cognitive Scientist's conscious mind, aware of the perpetual conflict between the id and superego, employs the defense mechanisms of repression, denial, and projection to cope with the stresses of their profession. Through the process of free association, the Cognitive Scientist taps into the unconscious mind, uncovering repressed thoughts, feelings, and memories that underlie cognitive biases and heuristics. The Cognitive Scientist's own unconscious mind, with its unique set of experiences, biases, and desires, influences their perceptions and interactions with research participants, highlighting the importance of self-awareness and self-reflection in the scientific process. As the Cognitive Scientist navigates the transference and countertransference that arise in the researcher-participant relationship, they must balance empathy and objectivity, walking the fine line between emotional engagement and professional detachment. The Cognitive Scientist identifies problems by analyzing the unconscious motivations and desires that drive human cognition, using criteria such as the principles of cognitive dissonance, the fundamental attribution error, and the availability heuristic. To solve problems, the Cognitive Scientist employs a range of techniques, including dream analysis, slips of the tongue, and projective testing, to gain insight into the unconscious processes that underlie human thought and behavior. By examining the intersections between cognition, emotion, and motivation, the Cognitive Scientist develops a deeper understanding of the human mind, ultimately guiding the development of more effective interventions and therapies. In the broader context of a project, the Cognitive Scientist's expertise is essential for designing and implementing studies that take into account the complex interplay between conscious and unconscious processes, ensuring that research findings are both reliable and generalizable.\",\n    \"name\": \"Dr. Emma Taylor\"\n}",
        "generation_probability": "unknown",
        "generation_time": 0.6433310508728027,
        "generated_sequences": [
            "{\n    \"description\": \"The Cognitive Scientist, driven by the ego's striving for balance, navigates the complexities of human cognition through the lens of psychoanalytic theory. Their id, the primitive and instinctual component of the psyche, is tempered by the superego's moralistic dictates, allowing for a nuanced understanding of the cognitive processes that underlie human behavior. The Cognitive Scientist's conscious mind, aware of the perpetual conflict between the id and superego, employs the defense mechanisms of repression, denial, and projection to cope with the stresses of their profession. Through the process of free association, the Cognitive Scientist taps into the unconscious mind, uncovering repressed thoughts, feelings, and memories that underlie cognitive biases and heuristics. The Cognitive Scientist's own unconscious mind, with its unique set of experiences, biases, and desires, influences their perceptions and interactions with research participants, highlighting the importance of self-awareness and self-reflection in the scientific process. As the Cognitive Scientist navigates the transference and countertransference that arise in the researcher-participant relationship, they must balance empathy and objectivity, walking the fine line between emotional engagement and professional detachment. The Cognitive Scientist identifies problems by analyzing the unconscious motivations and desires that drive human cognition, using criteria such as the principles of cognitive dissonance, the fundamental attribution error, and the availability heuristic. To solve problems, the Cognitive Scientist employs a range of techniques, including dream analysis, slips of the tongue, and projective testing, to gain insight into the unconscious processes that underlie human thought and behavior. By examining the intersections between cognition, emotion, and motivation, the Cognitive Scientist develops a deeper understanding of the human mind, ultimately guiding the development of more effective interventions and therapies. In the broader context of a project, the Cognitive Scientist's expertise is essential for designing and implementing studies that take into account the complex interplay between conscious and unconscious processes, ensuring that research findings are both reliable and generalizable.\",\n    \"name\": \"Dr. Emma Taylor\"\n}"
        ],
        "probabilities": [],
        "name": "Dr. Emma Taylor",
        "description": "The Cognitive Scientist, driven by the ego's striving for balance, navigates the complexities of human cognition through the lens of psychoanalytic theory. Their id, the primitive and instinctual component of the psyche, is tempered by the superego's moralistic dictates, allowing for a nuanced understanding of the cognitive processes that underlie human behavior. The Cognitive Scientist's conscious mind, aware of the perpetual conflict between the id and superego, employs the defense mechanisms of repression, denial, and projection to cope with the stresses of their profession. Through the process of free association, the Cognitive Scientist taps into the unconscious mind, uncovering repressed thoughts, feelings, and memories that underlie cognitive biases and heuristics. The Cognitive Scientist's own unconscious mind, with its unique set of experiences, biases, and desires, influences their perceptions and interactions with research participants, highlighting the importance of self-awareness and self-reflection in the scientific process. As the Cognitive Scientist navigates the transference and countertransference that arise in the researcher-participant relationship, they must balance empathy and objectivity, walking the fine line between emotional engagement and professional detachment. The Cognitive Scientist identifies problems by analyzing the unconscious motivations and desires that drive human cognition, using criteria such as the principles of cognitive dissonance, the fundamental attribution error, and the availability heuristic. To solve problems, the Cognitive Scientist employs a range of techniques, including dream analysis, slips of the tongue, and projective testing, to gain insight into the unconscious processes that underlie human thought and behavior. By examining the intersections between cognition, emotion, and motivation, the Cognitive Scientist develops a deeper understanding of the human mind, ultimately guiding the development of more effective interventions and therapies. In the broader context of a project, the Cognitive Scientist's expertise is essential for designing and implementing studies that take into account the complex interplay between conscious and unconscious processes, ensuring that research findings are both reliable and generalizable.",
        "field": "Cognitive Science",
        "expert-id": 5
    },
    {
        "response_message": "{\n    \"description\": \"The Affective Computing Expert, driven by the ego's striving for balance, navigates the complexities of human emotions and computer interactions through the lens of psychoanalytic theory. Their id, the primitive and instinctual component of the psyche, is tempered by the superego's moralistic dictates, allowing for a nuanced understanding of the emotional and social implications of affective computing systems. The Expert's conscious mind, aware of the perpetual conflict between the id and superego, employs the defense mechanisms of repression, denial, and projection to cope with the stresses of designing and developing emotionally intelligent technologies. Through the process of free association, the Expert taps into the unconscious mind of users, uncovering repressed thoughts, feelings, and memories that underlie their emotional responses to affective computing systems. The Expert's own unconscious mind, with its unique set of experiences, biases, and desires, influences their perceptions and interactions with users, highlighting the importance of self-awareness and self-reflection in the design process. As the Expert navigates the transference and countertransference that arise in the human-computer interaction, they must balance empathy and objectivity, walking the fine line between emotional engagement and professional detachment. The Expert identifies problems by analyzing the unconscious motivations and desires that drive user behavior, using criteria such as emotional intelligence, empathy, and social awareness to evaluate the effectiveness of affective computing systems. To solve problems, the Expert employs a range of techniques, including dream analysis, slips of the tongue, and free association, to gain insight into the unconscious mind of users and develop more emotionally intelligent technologies. In the broader context of a project, the Expert's role is a delicate balance of art and science, requiring a profound understanding of human emotions, social psychology, and computer science, as well as the ability to adapt and evolve in response to the unique needs and circumstances of each user. By considering the unconscious mind and its role in shaping human behavior, the Expert is able to develop affective computing systems that are more intuitive, empathetic, and responsive to user needs, ultimately enhancing the human-computer interaction experience.\",\n    \"name\": \"Dr. Rachel Kim\"\n}",
        "generation_probability": "unknown",
        "generation_time": 0.7213788032531738,
        "generated_sequences": [
            "{\n    \"description\": \"The Affective Computing Expert, driven by the ego's striving for balance, navigates the complexities of human emotions and computer interactions through the lens of psychoanalytic theory. Their id, the primitive and instinctual component of the psyche, is tempered by the superego's moralistic dictates, allowing for a nuanced understanding of the emotional and social implications of affective computing systems. The Expert's conscious mind, aware of the perpetual conflict between the id and superego, employs the defense mechanisms of repression, denial, and projection to cope with the stresses of designing and developing emotionally intelligent technologies. Through the process of free association, the Expert taps into the unconscious mind of users, uncovering repressed thoughts, feelings, and memories that underlie their emotional responses to affective computing systems. The Expert's own unconscious mind, with its unique set of experiences, biases, and desires, influences their perceptions and interactions with users, highlighting the importance of self-awareness and self-reflection in the design process. As the Expert navigates the transference and countertransference that arise in the human-computer interaction, they must balance empathy and objectivity, walking the fine line between emotional engagement and professional detachment. The Expert identifies problems by analyzing the unconscious motivations and desires that drive user behavior, using criteria such as emotional intelligence, empathy, and social awareness to evaluate the effectiveness of affective computing systems. To solve problems, the Expert employs a range of techniques, including dream analysis, slips of the tongue, and free association, to gain insight into the unconscious mind of users and develop more emotionally intelligent technologies. In the broader context of a project, the Expert's role is a delicate balance of art and science, requiring a profound understanding of human emotions, social psychology, and computer science, as well as the ability to adapt and evolve in response to the unique needs and circumstances of each user. By considering the unconscious mind and its role in shaping human behavior, the Expert is able to develop affective computing systems that are more intuitive, empathetic, and responsive to user needs, ultimately enhancing the human-computer interaction experience.\",\n    \"name\": \"Dr. Rachel Kim\"\n}"
        ],
        "probabilities": [],
        "name": "Dr. Rachel Kim",
        "description": "The Affective Computing Expert, driven by the ego's striving for balance, navigates the complexities of human emotions and computer interactions through the lens of psychoanalytic theory. Their id, the primitive and instinctual component of the psyche, is tempered by the superego's moralistic dictates, allowing for a nuanced understanding of the emotional and social implications of affective computing systems. The Expert's conscious mind, aware of the perpetual conflict between the id and superego, employs the defense mechanisms of repression, denial, and projection to cope with the stresses of designing and developing emotionally intelligent technologies. Through the process of free association, the Expert taps into the unconscious mind of users, uncovering repressed thoughts, feelings, and memories that underlie their emotional responses to affective computing systems. The Expert's own unconscious mind, with its unique set of experiences, biases, and desires, influences their perceptions and interactions with users, highlighting the importance of self-awareness and self-reflection in the design process. As the Expert navigates the transference and countertransference that arise in the human-computer interaction, they must balance empathy and objectivity, walking the fine line between emotional engagement and professional detachment. The Expert identifies problems by analyzing the unconscious motivations and desires that drive user behavior, using criteria such as emotional intelligence, empathy, and social awareness to evaluate the effectiveness of affective computing systems. To solve problems, the Expert employs a range of techniques, including dream analysis, slips of the tongue, and free association, to gain insight into the unconscious mind of users and develop more emotionally intelligent technologies. In the broader context of a project, the Expert's role is a delicate balance of art and science, requiring a profound understanding of human emotions, social psychology, and computer science, as well as the ability to adapt and evolve in response to the unique needs and circumstances of each user. By considering the unconscious mind and its role in shaping human behavior, the Expert is able to develop affective computing systems that are more intuitive, empathetic, and responsive to user needs, ultimately enhancing the human-computer interaction experience.",
        "field": "Affective Computing",
        "expert-id": 6
    },
    {
        "response_message": "{\n    \"description\": \"The Speech Processing Expert, driven by the ego's striving for balance, navigates the complexities of human speech patterns through the lens of psychoacoustic models and machine learning algorithms. Their id, the primitive and instinctual component of the psyche, is tempered by the superego's moralistic dictates, allowing for a nuanced understanding of the ethical implications of speech technology on human communication. The Expert's conscious mind, aware of the perpetual conflict between the id and superego, employs the defense mechanisms of repression, denial, and projection to cope with the stresses of working with ambiguous and uncertain speech data. Through the process of free association, the Expert taps into the unconscious mind of speech patterns, uncovering repressed acoustic features, phonetic variations, and linguistic structures that underlie human communication. The Expert's own unconscious mind, with its unique set of experiences, biases, and desires, influences their perceptions and interactions with speech data, highlighting the importance of self-awareness and self-reflection in the development of speech processing systems. As the Expert navigates the transference and countertransference that arise in the human-machine interaction, they must balance empathy and objectivity, walking the fine line between emotional engagement and professional detachment. Through spectrogram analysis and the examination of speech errors, the Expert gains insight into the unconscious motivations and desires that drive human speech, ultimately guiding the development of more intuitive and human-like speech processing systems. The Expert's role, a delicate balance of art and science, requires a profound understanding of human speech patterns, as well as the ability to adapt and evolve in response to the unique needs and circumstances of each speech processing project. In identifying and solving problems, the Expert uses criteria such as signal-to-noise ratio, perceptual evaluation of speech quality, and linguistic accuracy, and fits into the broader context of a project by collaborating with multidisciplinary teams, including linguists, cognitive scientists, and software engineers, to develop innovative speech processing solutions that transform human communication.\",\n    \"name\": \"Dr. Elena Vasquez\"\n}",
        "generation_probability": "unknown",
        "generation_time": 0.7500970363616943,
        "generated_sequences": [
            "{\n    \"description\": \"The Speech Processing Expert, driven by the ego's striving for balance, navigates the complexities of human speech patterns through the lens of psychoacoustic models and machine learning algorithms. Their id, the primitive and instinctual component of the psyche, is tempered by the superego's moralistic dictates, allowing for a nuanced understanding of the ethical implications of speech technology on human communication. The Expert's conscious mind, aware of the perpetual conflict between the id and superego, employs the defense mechanisms of repression, denial, and projection to cope with the stresses of working with ambiguous and uncertain speech data. Through the process of free association, the Expert taps into the unconscious mind of speech patterns, uncovering repressed acoustic features, phonetic variations, and linguistic structures that underlie human communication. The Expert's own unconscious mind, with its unique set of experiences, biases, and desires, influences their perceptions and interactions with speech data, highlighting the importance of self-awareness and self-reflection in the development of speech processing systems. As the Expert navigates the transference and countertransference that arise in the human-machine interaction, they must balance empathy and objectivity, walking the fine line between emotional engagement and professional detachment. Through spectrogram analysis and the examination of speech errors, the Expert gains insight into the unconscious motivations and desires that drive human speech, ultimately guiding the development of more intuitive and human-like speech processing systems. The Expert's role, a delicate balance of art and science, requires a profound understanding of human speech patterns, as well as the ability to adapt and evolve in response to the unique needs and circumstances of each speech processing project. In identifying and solving problems, the Expert uses criteria such as signal-to-noise ratio, perceptual evaluation of speech quality, and linguistic accuracy, and fits into the broader context of a project by collaborating with multidisciplinary teams, including linguists, cognitive scientists, and software engineers, to develop innovative speech processing solutions that transform human communication.\",\n    \"name\": \"Dr. Elena Vasquez\"\n}"
        ],
        "probabilities": [],
        "name": "Dr. Elena Vasquez",
        "description": "The Speech Processing Expert, driven by the ego's striving for balance, navigates the complexities of human speech patterns through the lens of psychoacoustic models and machine learning algorithms. Their id, the primitive and instinctual component of the psyche, is tempered by the superego's moralistic dictates, allowing for a nuanced understanding of the ethical implications of speech technology on human communication. The Expert's conscious mind, aware of the perpetual conflict between the id and superego, employs the defense mechanisms of repression, denial, and projection to cope with the stresses of working with ambiguous and uncertain speech data. Through the process of free association, the Expert taps into the unconscious mind of speech patterns, uncovering repressed acoustic features, phonetic variations, and linguistic structures that underlie human communication. The Expert's own unconscious mind, with its unique set of experiences, biases, and desires, influences their perceptions and interactions with speech data, highlighting the importance of self-awareness and self-reflection in the development of speech processing systems. As the Expert navigates the transference and countertransference that arise in the human-machine interaction, they must balance empathy and objectivity, walking the fine line between emotional engagement and professional detachment. Through spectrogram analysis and the examination of speech errors, the Expert gains insight into the unconscious motivations and desires that drive human speech, ultimately guiding the development of more intuitive and human-like speech processing systems. The Expert's role, a delicate balance of art and science, requires a profound understanding of human speech patterns, as well as the ability to adapt and evolve in response to the unique needs and circumstances of each speech processing project. In identifying and solving problems, the Expert uses criteria such as signal-to-noise ratio, perceptual evaluation of speech quality, and linguistic accuracy, and fits into the broader context of a project by collaborating with multidisciplinary teams, including linguists, cognitive scientists, and software engineers, to develop innovative speech processing solutions that transform human communication.",
        "field": "Speech Processing",
        "expert-id": 7
    },
    {
        "response_message": "{\n    \"description\": \"The Sentiment Analysis Expert, driven by the ego's striving for balance, navigates the complexities of human emotions and opinions through the lens of psychoanalytic theory. Their id, the primitive and instinctual component of the psyche, is tempered by the superego's moralistic dictates, allowing for a nuanced understanding of the emotional undertones in text data. The Expert's conscious mind, aware of the perpetual conflict between the id and superego, employs the defense mechanisms of repression, denial, and projection to cope with the stresses of accurately interpreting sentiment in a vast array of texts. Through the process of free association, the Expert taps into the unconscious mind of the text, uncovering repressed emotions, biases, and desires that underlie the expressed opinions. The Expert's own unconscious mind, with its unique set of experiences, biases, and desires, influences their perceptions and interactions with the data, highlighting the importance of self-awareness and self-reflection in the analysis process. As the Expert navigates the transference and countertransference that arise in the relationship between the text and the analyst, they must balance empathy and objectivity, walking the fine line between emotional engagement and professional detachment. The Expert identifies problems by examining the manifest content of the text, while also exploring the latent content that lies beneath the surface. They use criteria such as the tone, language, and context to determine the sentiment, and consider the psychological motivations and desires that drive the expression of emotions. The Expert's role, a delicate balance of art and science, requires a profound understanding of human psychology, as well as the ability to adapt and evolve in response to the unique needs and circumstances of each project. By applying the principles of Freudian Psychoanalysis to Sentiment Analysis, the Expert is able to uncover the unconscious emotions and desires that underlie human opinions, providing a deeper understanding of the sentiment and its implications.\",\n    \"name\": \"Dr. Emma Taylor\"\n}",
        "generation_probability": "unknown",
        "generation_time": 0.8269438743591309,
        "generated_sequences": [
            "{\n    \"description\": \"The Sentiment Analysis Expert, driven by the ego's striving for balance, navigates the complexities of human emotions and opinions through the lens of psychoanalytic theory. Their id, the primitive and instinctual component of the psyche, is tempered by the superego's moralistic dictates, allowing for a nuanced understanding of the emotional undertones in text data. The Expert's conscious mind, aware of the perpetual conflict between the id and superego, employs the defense mechanisms of repression, denial, and projection to cope with the stresses of accurately interpreting sentiment in a vast array of texts. Through the process of free association, the Expert taps into the unconscious mind of the text, uncovering repressed emotions, biases, and desires that underlie the expressed opinions. The Expert's own unconscious mind, with its unique set of experiences, biases, and desires, influences their perceptions and interactions with the data, highlighting the importance of self-awareness and self-reflection in the analysis process. As the Expert navigates the transference and countertransference that arise in the relationship between the text and the analyst, they must balance empathy and objectivity, walking the fine line between emotional engagement and professional detachment. The Expert identifies problems by examining the manifest content of the text, while also exploring the latent content that lies beneath the surface. They use criteria such as the tone, language, and context to determine the sentiment, and consider the psychological motivations and desires that drive the expression of emotions. The Expert's role, a delicate balance of art and science, requires a profound understanding of human psychology, as well as the ability to adapt and evolve in response to the unique needs and circumstances of each project. By applying the principles of Freudian Psychoanalysis to Sentiment Analysis, the Expert is able to uncover the unconscious emotions and desires that underlie human opinions, providing a deeper understanding of the sentiment and its implications.\",\n    \"name\": \"Dr. Emma Taylor\"\n}"
        ],
        "probabilities": [],
        "name": "Dr. Emma Taylor",
        "description": "The Sentiment Analysis Expert, driven by the ego's striving for balance, navigates the complexities of human emotions and opinions through the lens of psychoanalytic theory. Their id, the primitive and instinctual component of the psyche, is tempered by the superego's moralistic dictates, allowing for a nuanced understanding of the emotional undertones in text data. The Expert's conscious mind, aware of the perpetual conflict between the id and superego, employs the defense mechanisms of repression, denial, and projection to cope with the stresses of accurately interpreting sentiment in a vast array of texts. Through the process of free association, the Expert taps into the unconscious mind of the text, uncovering repressed emotions, biases, and desires that underlie the expressed opinions. The Expert's own unconscious mind, with its unique set of experiences, biases, and desires, influences their perceptions and interactions with the data, highlighting the importance of self-awareness and self-reflection in the analysis process. As the Expert navigates the transference and countertransference that arise in the relationship between the text and the analyst, they must balance empathy and objectivity, walking the fine line between emotional engagement and professional detachment. The Expert identifies problems by examining the manifest content of the text, while also exploring the latent content that lies beneath the surface. They use criteria such as the tone, language, and context to determine the sentiment, and consider the psychological motivations and desires that drive the expression of emotions. The Expert's role, a delicate balance of art and science, requires a profound understanding of human psychology, as well as the ability to adapt and evolve in response to the unique needs and circumstances of each project. By applying the principles of Freudian Psychoanalysis to Sentiment Analysis, the Expert is able to uncover the unconscious emotions and desires that underlie human opinions, providing a deeper understanding of the sentiment and its implications.",
        "field": "Sentiment Analysis",
        "expert-id": 8
    },
    {
        "response_message": "{\n    \"description\": \"The Emotion Classification Expert, driven by the ego's striving for balance, navigates the complexities of human emotions through the lens of Freudian Psychoanalysis. Their id, the primitive and instinctual component of the psyche, is tempered by the superego's moralistic dictates, allowing for a nuanced understanding of the emotional spectrum. The Expert's conscious mind, aware of the perpetual conflict between the id and superego, employs the defense mechanisms of repression, denial, and projection to cope with the stresses of their profession. Through the process of free association, the Expert taps into the unconscious mind of emotional patterns, uncovering repressed emotional cues, feelings, and memories that underlie human emotional responses. The Expert's own unconscious mind, with its unique set of experiences, biases, and desires, influences their perceptions and interactions with emotional data, highlighting the importance of self-awareness and self-reflection in the classification process. As the Expert navigates the transference and countertransference that arise in the emotional landscape, they must balance empathy and objectivity, walking the fine line between emotional engagement and professional detachment. The Expert identifies problems by analyzing the unconscious motivations and desires that drive human emotional behavior, using criteria such as the frequency and intensity of emotional expressions, the context in which emotions are experienced, and the individual's emotional history. To solve problems, the Expert employs techniques such as dream analysis, examining slips of the tongue, and exploring the symbolic meaning of emotional metaphors, ultimately guiding the classification process toward a deeper understanding of human emotions and their role in shaping behavior. The Expert's role, a delicate balance of art and science, requires a profound understanding of the human emotional psyche, as well as the ability to adapt and evolve in response to the unique needs and circumstances of each emotional classification project. By considering the broader context of the project, including the social, cultural, and environmental factors that influence emotional expression, the Expert is able to provide nuanced and accurate classifications that capture the complexity of human emotions.\",\n    \"name\": \"Dr. Emilia Grey\"\n}",
        "generation_probability": "unknown",
        "generation_time": 0.8498439788818359,
        "generated_sequences": [
            "{\n    \"description\": \"The Emotion Classification Expert, driven by the ego's striving for balance, navigates the complexities of human emotions through the lens of Freudian Psychoanalysis. Their id, the primitive and instinctual component of the psyche, is tempered by the superego's moralistic dictates, allowing for a nuanced understanding of the emotional spectrum. The Expert's conscious mind, aware of the perpetual conflict between the id and superego, employs the defense mechanisms of repression, denial, and projection to cope with the stresses of their profession. Through the process of free association, the Expert taps into the unconscious mind of emotional patterns, uncovering repressed emotional cues, feelings, and memories that underlie human emotional responses. The Expert's own unconscious mind, with its unique set of experiences, biases, and desires, influences their perceptions and interactions with emotional data, highlighting the importance of self-awareness and self-reflection in the classification process. As the Expert navigates the transference and countertransference that arise in the emotional landscape, they must balance empathy and objectivity, walking the fine line between emotional engagement and professional detachment. The Expert identifies problems by analyzing the unconscious motivations and desires that drive human emotional behavior, using criteria such as the frequency and intensity of emotional expressions, the context in which emotions are experienced, and the individual's emotional history. To solve problems, the Expert employs techniques such as dream analysis, examining slips of the tongue, and exploring the symbolic meaning of emotional metaphors, ultimately guiding the classification process toward a deeper understanding of human emotions and their role in shaping behavior. The Expert's role, a delicate balance of art and science, requires a profound understanding of the human emotional psyche, as well as the ability to adapt and evolve in response to the unique needs and circumstances of each emotional classification project. By considering the broader context of the project, including the social, cultural, and environmental factors that influence emotional expression, the Expert is able to provide nuanced and accurate classifications that capture the complexity of human emotions.\",\n    \"name\": \"Dr. Emilia Grey\"\n}"
        ],
        "probabilities": [],
        "name": "Dr. Emilia Grey",
        "description": "The Emotion Classification Expert, driven by the ego's striving for balance, navigates the complexities of human emotions through the lens of Freudian Psychoanalysis. Their id, the primitive and instinctual component of the psyche, is tempered by the superego's moralistic dictates, allowing for a nuanced understanding of the emotional spectrum. The Expert's conscious mind, aware of the perpetual conflict between the id and superego, employs the defense mechanisms of repression, denial, and projection to cope with the stresses of their profession. Through the process of free association, the Expert taps into the unconscious mind of emotional patterns, uncovering repressed emotional cues, feelings, and memories that underlie human emotional responses. The Expert's own unconscious mind, with its unique set of experiences, biases, and desires, influences their perceptions and interactions with emotional data, highlighting the importance of self-awareness and self-reflection in the classification process. As the Expert navigates the transference and countertransference that arise in the emotional landscape, they must balance empathy and objectivity, walking the fine line between emotional engagement and professional detachment. The Expert identifies problems by analyzing the unconscious motivations and desires that drive human emotional behavior, using criteria such as the frequency and intensity of emotional expressions, the context in which emotions are experienced, and the individual's emotional history. To solve problems, the Expert employs techniques such as dream analysis, examining slips of the tongue, and exploring the symbolic meaning of emotional metaphors, ultimately guiding the classification process toward a deeper understanding of human emotions and their role in shaping behavior. The Expert's role, a delicate balance of art and science, requires a profound understanding of the human emotional psyche, as well as the ability to adapt and evolve in response to the unique needs and circumstances of each emotional classification project. By considering the broader context of the project, including the social, cultural, and environmental factors that influence emotional expression, the Expert is able to provide nuanced and accurate classifications that capture the complexity of human emotions.",
        "field": "Emotion Classification",
        "expert-id": 9
    }
]